Workbook

Sheet Total 2024
A1: -+ | B1: Despesas | C1: Receita | D1: Saldo | F1: Despesa Total 2024 | G1: Receita Total 2024 | H1: Saldo Total 2024
A2: Março | B2: =('Março'!E1) -> 1962.12 | C2: 2162 | D2: =C2-B2 -> 199.88 | F2: =SUM(B2:B11) -> 14220.44 | G2: =SUM(C2:C11) -> 19693 | H2: =SUM(D2:D11) -> 5472.56
A3: Abril | B3: =(Abril!E1) -> 1676.33 | C3: 1876 | D3: =C3-B3 -> 199.67
A4: Maio | B4: =(Maio!E1) -> 1305.83 | C4: 1505 | D4: =C4-B4 -> 199.17
A5: Junho | B5: =(Junho!E1) -> 1372 | C5: 1572 | D5: =C5-B5 -> 200
A6: Julho | B6: =(Julho!E1) -> 1330.9 | C6: 1830 | D6: =C6-B6 -> 499.1
A7: Agosto | B7: =(Agosto!E1) -> 1355.3 | C7: 1555 | D7: =C7-B7 -> 199.7
A8: Setembro | B8: =(Setembro!F2) -> 1213.5 | C8: =(Setembro!G2) -> 1661 | D8: =C8-B8 -> 447.5
A9: Outubro | B9: =(Outubro!F2) -> 1427 | C9: =(Outubro!G2) -> 1979 | D9: =C9-B9 -> 552
A10: Novembro | B10: =(Novembro!F2) -> 1080.34 | C10: =(Novembro!G2) -> 2859 | D10: =C10-B10 -> 1778.66
A11: Dezembro | B11: =(Dezembro!F2) -> 1497.12 | C11: =(Dezembro!G2) -> 2694 | D11: =C11-B11 -> 1196.88

Sheet Março
A1: 45352 | B1: sexta-feira | C1: 5.5 | D1: Açucar, Pão de queijo | E1: =SUM(C1:C31) -> 1962.12
A2: 45353 | B2: sábado | C2: 0 | D2: None
A3: 45354 | B3: domingo | C3: 18.88 | D3: Sorvete
A4: 45355 | B4: segunda-feira | C4: 4.5 | D4: Caldo de cana
A5: 45356 | B5: terça-feira | C5: 0
A6: 45357 | B6: quarta-feira | C6: 0
A7: 45358 | B7: quinta-feira | C7: 7 | D7: Salgado e suco
A8: 45359 | B8: sexta-feira | C8: 200 | D8: Mãe
A9: 45360 | B9: sábado | C9: 30.1 | D9: Táxi, almoço
A10: 45361 | B10: domingo | C10: 30 | D10: Internet
A11: 45362 | B11: segunda-feira | C11: 4.5 | D11: Caldo de cana
A12: 45363 | B12: terça-feira | C12: 846 | D12: Guarda chuva (23) + auto escola
A13: 45364 | B13: quarta-feira | C13: 0
A14: 45365 | B14: quinta-feira | C14: 100 | D14: Mãe
A15: 45366 | B15: sexta-feira | C15: 0
A16: 45367 | B16: sábado | C16: 16 | D16: Salgados e refrigerante
A17: 45368 | B17: domingo | C17: 15.75 | D17: sorvete
A18: 45369 | B18: segunda-feira | C18: 20 | D18: almoço
A19: 45370 | B19: terça-feira | C19: 159.25 | D19: Mãe e Lanche
A20: 45371 | B20: quarta-feira | C20: 75.99 | D20: Lanche (16) e Camisa Elegance (59,99)
A21: 45372 | B21: quinta-feira | C21: 4.5 | D21: Caldo de cana
A22: 45373 | B22: sexta-feira | C22: 7 | D22: Pão de queijo e caldo de cana
A23: 45374 | B23: sábado | C23: 74.5 | D23: Presente da fernanda, Caldo de cana, Participação no salgado da Moda Show e Mãe
A24: 45375 | B24: domingo | C24: 28 | D24: Milkshake
A25: 45376 | B25: segunda-feira | C25: 24.5 | D25: Lanches diversos dias
A26: 45377 | B26: terça-feira | C26: 30 | D26: Internet
A27: 45378 | B27: quarta-feira | C27: 0
A28: 45379 | B28: quinta-feira | C28: 0
A29: 45380 | B29: sexta-feira | C29: 58.7 | D29: Sorvete + Brawn stars pass
A30: 45381 | B30: sábado | C30: 153 | D30: Caixa de bombom + Sprite (16) + almoço (27) + uber (10) + Mãe (100)
A31: 45382 | B31: domingo | C31: 48.45 | D31: refrigerante e sorvete

Sheet Abril
A1: 45383 | B1: segunda-feira | C1: 0 | E1: =SUM(C1:C31) -> 1676.33
A2: 45384 | B2: terça-feira | C2: 0
A3: 45385 | B3: quarta-feira | C3: 7.5 | D3: Caldo de cana e chokito
A4: 45386 | B4: quinta-feira | C4: 39.9 | D4: Brawn stars
A5: 45387 | B5: sexta-feira | C5: 28 | D5: Pizza a noite
A6: 45388 | B6: sábado | C6: 310.09 | D6: Calça Teezz (85,99), Uber moto (20), Saida a noite (144,10) uber (30), Mãe (30)
A7: 45389 | B7: domingo | C7: 21.74 | D7: Sorvete
A8: 45390 | B8: segunda-feira | C8: 0
A9: 45391 | B9: terça-feira | C9: 42 | D9: presente aniversário Gustavo
A10: 45392 | B10: quarta-feira | C10: 25 | D10: Guarda chuva pra mãe
A11: 45393 | B11: quinta-feira | C11: 100 | D11: presente aniversário Sheila (Março)
A12: 45394 | B12: sexta-feira | C12: 130 | D12: Maquina de barbear
A13: 45395 | B13: sábado | C13: 80 | D13: Uber ida e volta, milkshake, pass brawn stars (gustavo)
A14: 45396 | B14: domingo | C14: 330 | D14: Auto Escola
A15: 45397 | B15: segunda-feira | C15: 145 | D15: Mãe (130), Lanches
A16: 45398 | B16: terça-feira | C16: 153.5 | D16: Mãe (150), suco
A17: 45399 | B17: quarta-feira | C17: 0
A18: 45400 | B18: quinta-feira | C18: 0
A19: 45401 | B19: sexta-feira | C19: 44.6 | D19: Mãe (15), lanches diversos dias
A20: 45402 | B20: sábado | C20: 10 | D20: Mãe
A21: 45403 | B21: domingo | C21: 36 | D21: Sorvete
A22: 45404 | B22: segunda-feira | C22: 63.5 | D22: Cuecas e Suco (3,50)
A23: 45405 | B23: terça-feira | C23: 9.5 | D23: Caldo de cana e salgado
A24: 45406 | B24: quarta-feira | C24: 0
A25: 45407 | B25: quinta-feira | C25: 0
A26: 45408 | B26: sexta-feira | C26: 0
A27: 45409 | B27: sábado | C27: 0
A28: 45410 | B28: domingo | C28: 70 | D28: Minas shopping
A29: 45411 | B29: segunda-feira | C29: 0
A30: 45412 | B30: terça-feira | C30: 30 | D30: Almoço

Sheet Maio
A1: 45413 | B1: quarta-feira | E1: =SUM(C1:C31) -> 1305.83
A2: 45414 | B2: quinta-feira
A3: 45415 | B3: sexta-feira | C3: 331 | D3: 225 reconhecimento de pista, 100 Mãe, 6 refrigerante
A4: 45416 | B4: sábado | C4: 3.8 | D4: Limonada
A5: 45417 | B5: domingo
A6: 45418 | B6: segunda-feira | C6: 16.55 | D6: lanches em geral
A7: 45419 | B7: terça-feira
A8: 45420 | B8: quarta-feira | C8: 113.8 | D8: Auto Escola (13), presente dia das mães (85), sorvete (12), Suco (3,80)
A9: 45421 | B9: quinta-feira
A10: 45422 | B10: sexta-feira
A11: 45423 | B11: sábado | C11: 60 | D11: Celeste
A12: 45424 | B12: domingo | C12: 57 | D12: Sorvete, Chocolate, gastos em geral
A13: 45425 | B13: segunda-feira
A14: 45426 | B14: terça-feira
A15: 45427 | B15: quarta-feira
A16: 45428 | B16: quinta-feira | C16: 117.45 | D16: Mãe (100), Lanches gerais
A17: 45429 | B17: sexta-feira
A18: 45430 | B18: sábado
A19: 45431 | B19: domingo | C19: 214 | D19: Mãe (200), Milk shake
A20: 45432 | B20: segunda-feira
A21: 45433 | B21: terça-feira
A22: 45434 | B22: quarta-feira | C22: 7.3 | D22: Caldo de Cana e Chokito
A23: 45435 | B23: quinta-feira
A24: 45436 | B24: sexta-feira | C24: 67.6 | D24: Café da manhã, lanche e mãe (50)
A25: 45437 | B25: sábado
A26: 45438 | B26: domingo | C26: 70.45 | D26: Sorvete, Mãe (50)
A27: 45439 | B27: segunda-feira
A28: 45440 | B28: terça-feira | C28: 59.74 | D28: Creme para pentear, desodorante (54,98), trento (4,76)
A29: 45441 | B29: quarta-feira | C29: 27.5 | D29: Sprite, Mãe (20)
A30: 45442 | B30: quinta-feira | C30: 26.65 | D30: Sorvete
A31: 45443 | B31: sexta-feira | C31: 132.99 | D31: Mãe, Calça Teezz (85,99)

Sheet Junho
A1: 45444 | B1: sábado | C1: 38 | D1: Presente aniversário luna | E1: =SUM(C1:C31) -> 1372
A2: 45445 | B2: domingo | C2: 270 | D2: Cadeira
A3: 45446 | B3: segunda-feira
A4: 45447 | B4: terça-feira
A5: 45448 | B5: quarta-feira | C5: 500 | D5: Aluguel
A6: 45449 | B6: quinta-feira | C6: 7 | D6: Trento e Chokito
A7: 45450 | B7: sexta-feira
A8: 45451 | B8: sábado
A9: 45452 | B9: domingo | C9: 20 | D9: Macarrão na Chapa
A10: 45453 | B10: segunda-feira | C10: 50 | D10: Tinta da calça
A11: 45454 | B11: terça-feira | C11: 3.8 | D11: Suco almoço
A12: 45455 | B12: quarta-feira
A13: 45456 | B13: quinta-feira
A14: 45457 | B14: sexta-feira
A15: 45458 | B15: sábado | C15: 28 | D15: sorvete, cappucino, pão de queijo
A16: 45459 | B16: domingo | C16: 28 | D16: pão de queijo, refrigerante, pão de mel
A17: 45460 | B17: segunda-feira | C17: 65 | D17: sorvete, Mãe (20)
A18: 45461 | B18: terça-feira | C18: 50 | D18: Garrafas (20), Mãe (30)
A19: 45462 | B19: quarta-feira
A20: 45463 | B20: quinta-feira
A21: 45464 | B21: sexta-feira | C21: 100 | D21: Mãe
A22: 45465 | B22: sábado | C22: 62 | D22: Ida no nazaré, The Coffin of Andy and Leyley (32)
A23: 45466 | B23: domingo | C23: 20 | D23: Sorvete
A24: 45467 | B24: segunda-feira
A25: 45468 | B25: terça-feira
A26: 45469 | B26: quarta-feira
A27: 45470 | B27: quinta-feira
A28: 45471 | B28: sexta-feira
A29: 45472 | B29: sábado | C29: 16.2 | D29: Lanches diversos dias
A30: 45473 | B30: domingo | C30: 114 | D30: Sorvete e refrigerante (27), Mãe (50), Sorvete noite + mãe (37)

Sheet Julho
A1: 45474 | B1: segunda-feira | C1: 50 | D1: Mãe (50) | E1: =SUM(C1:C31) -> 1330.9
A2: 45475 | B2: terça-feira | C2: 25.5 | D2: Caldo de Cana, Hollow Knight
A3: 45476 | B3: quarta-feira
A4: 45477 | B4: quinta-feira | C4: 57 | D4: Brawn Stars, aniversário nilcea, salgado
A5: 45478 | B5: sexta-feira | C5: 500 | D5: Aluguel
A6: 45479 | B6: sábado | C6: 40 | D6: Uber ida e volta
A7: 45480 | B7: domingo
A8: 45481 | B8: segunda-feira | C8: 50 | D8: Mãe
A9: 45482 | B9: terça-feira | C9: 25 | D9: Desodorante, Pasta de Dente, Suco (3,80)
A10: 45483 | B10: quarta-feira
A11: 45484 | B11: quinta-feira
A12: 45485 | B12: sexta-feira
A13: 45486 | B13: sábado
A14: 45487 | B14: domingo
A15: 45488 | B15: segunda-feira | C15: 113 | D15: Calças chimpa e gastos diversos
A16: 45489 | B16: terça-feira
A17: 45490 | B17: quarta-feira
A18: 45491 | B18: quinta-feira
A19: 45492 | B19: sexta-feira | C19: 50.5 | D19: 17,50 (Enrolado e refrigerante) + 34 (Sanduiche)
A20: 45493 | B20: sábado | C20: 28.5 | D20: 15 (Metade da internet mãe) + 10 (Mãe) + 3,50 (Refrigerante)
A21: 45494 | B21: domingo | C21: 83.8 | D21: 3,80 (Suco) + 24 (Uber Volta) + 26 (despedida walquiria) + 30 (internet)
A22: 45495 | B22: segunda-feira | C22: 135 | D22: Mãe (100), Relaxante de cabelo (30), Salgado (5)
A23: 45496 | B23: terça-feira
A24: 45497 | B24: quarta-feira
A25: 45498 | B25: quinta-feira
A26: 45499 | B26: sexta-feira
A27: 45500 | B27: sábado
A28: 45501 | B28: domingo
A29: 45502 | B29: segunda-feira
A30: 45503 | B30: terça-feira | C30: 172.6 | D30: Ida no Cinema, Almoço 2 dias e Mãe
A31: 45504 | B31: quarta-feira

Sheet Agosto
A1: 45505 | B1: quinta-feira | E1: =SUM(C1:C31) -> 1355.3
A2: 45506 | B2: sexta-feira
A3: 45507 | B3: sábado
A4: 45508 | B4: domingo
A5: 45509 | B5: segunda-feira | C5: 500 | D5: Aluguel
A6: 45510 | B6: terça-feira | C6: 190.8 | D6: Internet (30), Sorvete (15), Suco (3,80), 142 (Geladeira)
A7: 45511 | B7: quarta-feira
A8: 45512 | B8: quinta-feira
A9: 45513 | B9: sexta-feira | C9: 32 | D9: Passagem, Cartão de passagem
A10: 45514 | B10: sábado | C10: 9.5 | D10: Doce, Refrigerante
A11: 45515 | B11: domingo | C11: 19 | D11: Sorvete
A12: 45516 | B12: segunda-feira
A13: 45517 | B13: terça-feira
A14: 45518 | B14: quarta-feira
A15: 45519 | B15: quinta-feira | C15: 80 | D15: Mãe
A16: 45520 | B16: sexta-feira | C16: 28 | D16: Sorvete
A17: 45521 | B17: sábado | C17: 75 | D17: Presente Victória, Corte de cabelo
A18: 45522 | B18: domingo | C18: 50 | D18: Mãe
A19: 45523 | B19: segunda-feira | C19: 132 | D19: Macarrão na Chapa, Mãe Uber Natale (90)
A20: 45524 | B20: terça-feira | C20: 28 | D20: Almoço
A21: 45525 | B21: quarta-feira | C21: 51 | D21: Lanche a noite
A22: 45526 | B22: quinta-feira
A23: 45527 | B23: sexta-feira
A24: 45528 | B24: sábado
A25: 45529 | B25: domingo
A26: 45530 | B26: segunda-feira
A27: 45531 | B27: terça-feira
A28: 45532 | B28: quarta-feira
A29: 45533 | B29: quinta-feira
A30: 45534 | B30: sexta-feira
A31: 45535 | B31: sábado | C31: 160 | D31: Suposição de gastos

Sheet Setembro
A1: Dia do Mês | B1: Dia da Semana | C1: Despesas | D1: Receitas | E1: Informação adicional | F1: Valor Gasto | G1: Valor Faturado | H1: Saldo
A2: 45536 | B2: domingo | F2: =SUM(C2:C31) -> 1213.5 | G2: =SUM(D2:D31) -> 1661 | H2: =G2-F2 -> 447.5
A3: 45537 | B3: segunda-feira | C3: 28 | E3: Almoço
A4: 45538 | B4: terça-feira | D4: 969 | E4: Salário
A5: 45539 | B5: quarta-feira
A6: 45540 | B6: quinta-feira | C6: 500 | E6: Aluguel
A7: 45541 | B7: sexta-feira | C7: 20 | E7: Pastel
A8: 45542 | B8: sábado | C8: 20 | D8: 20 | E8: Sorvete / Bonificação
A9: 45543 | B9: domingo | C9: 20 | E9: Sorvete
A10: 45544 | B10: segunda-feira
A11: 45545 | B11: terça-feira
A12: 45546 | B12: quarta-feira | C12: 100 | E12: Sheila
A13: 45547 | B13: quinta-feira | C13: 150 | E13: Guarda roupa
A14: 45548 | B14: sexta-feira | C14: 109 | E14: Geladeira
A15: 45549 | B15: sábado | D15: 20 | E15: Bonificação
A16: 45550 | B16: domingo
A17: 45551 | B17: segunda-feira
A18: 45552 | B18: terça-feira
A19: 45553 | B19: quarta-feira | D19: 632 | E19: (Adiantamento)
A20: 45554 | B20: quinta-feira
A21: 45555 | B21: sexta-feira
A22: 45556 | B22: sábado | C22: 88 | D22: 20 | E22: Lanche (50) + camisa UV (38) / Bonificação
A23: 45557 | B23: domingo | C23: 14 | E23: Sorvete
A24: 45558 | B24: segunda-feira
A25: 45559 | B25: terça-feira
A26: 45560 | B26: quarta-feira
A27: 45561 | B27: quinta-feira | C27: 30 | E27: Mãe
A28: 45562 | B28: sexta-feira | C28: 13.5 | E28: Paçoca, Pastel e Suco em dias diversos
A29: 45563 | B29: sábado | C29: 57 | E29: Almoço restaurante (27), Internet (30)
A30: 45564 | B30: domingo | C30: 14 | E30: Milkshake
A31: 45565 | B31: segunda-feira | C31: 50 | E31: Mãe

Sheet Outubro
A1: Dia do Mês | B1: Dia da Semana | C1: Despesas | D1: Receita | E1: Informação adicional | F1: Despesas | G1: Receita | H1: Saldo
A2: 45566 | B2: Terça-feira | C2: 0 | D2: 0 | F2: =SUM(C2:C32) -> 1427 | G2: =SUM(D2:D32) -> 1979 | H2: =G2-F2 -> 552
A3: 45567 | B3: quarta-feira | C3: 68 | E3: Camisa Uv Azul, Internet
A4: 45568 | B4: quinta-feira | D4: 1077 | E4: Salário
A5: 45569 | B5: sexta-feira | D5: 150 | E5: Remuneração Estoque
A6: 45570 | B6: sábado | C6: 528 | D6: 20 | E6: Aluguel, Almoço / Bonificação
A7: 45571 | B7: domingo | C7: 49 | E7: Sanduiche, Sorvete
A8: 45572 | B8: segunda-feira | C8: 25 | E8: 3 Pastas de Dente, Vitamina
A9: 45573 | B9: terça-feira
A10: 45574 | B10: quarta-feira
A11: 45575 | B11: quinta-feira | C11: 270 | E11: Transporte Geladeira Mãe (250) ; Edmar (20)
A12: 45576 | B12: sexta-feira | D12: 40 | E12: Edmar (20) / Bonificação
A13: 45577 | B13: sábado
A14: 45578 | B14: domingo | C14: 21 | E14: Sorvete
A15: 45579 | B15: segunda-feira | C15: 200 | E15: Mãe
A16: 45580 | B16: terça-feira | C16: 9 | E16: Refrigerante (7,50), caneta (1,50)
A17: 45581 | B17: quarta-feira | C17: 0
A18: 45582 | B18: quinta-feira | D18: 632 | E18: Adiantamento
A19: 45583 | B19: sexta-feira | C19: 9.5 | E19: Suco, Refrigerante
A20: 45584 | B20: sábado | C20: 40.5 | D20: 20 | E20: Doces, Sanduiche / Bonificação
A21: 45585 | B21: domingo | C21: 20 | D21: 10 | E21: Crunchyroll / Gustavo Crunchyroll
A22: 45586 | B22: segunda-feira | C22: 4 | E22: Suco
A23: 45587 | B23: terça-feira | C23: 86 | E23: Geladeira
A24: 45588 | B24: quarta-feira
A25: 45589 | B25: quinta-feira
A26: 45590 | B26: sexta-feira
A27: 45591 | B27: sábado | C27: 61.5 | D27: 20 | E27: Cachorro quente (ingredientes) / Bonificação
A28: 45592 | B28: domingo | C28: 22 | E28: Sorvete
A29: 45593 | B29: segunda-feira
A30: 45594 | B30: terça-feira | C30: 9.5 | E30: Lanche
A31: 45595 | B31: quarta-feira | C31: 4 | D31: 10 | E31: Lanche, Caneta p - vitória / Bonificação
A32: 45596 | B32: quinta-feira

Sheet Novembro
A1: Dia do Mês | B1: Dia da Semana | C1: Despesas | D1: Receitas | E1: Informação adicional | F1: Valor Gasto | G1: Valor Faturado | H1: Saldo
A2: 45597 | B2: Sexta-Feira | C2: 22 | D2: 20 | E2: Supermercado / Bonificação | F2: =SUM(C2:C31) -> 1080.34 | G2: =SUM(D2:D31) -> 2859 | H2: =G2-F2 -> 1778.66
A3: 45598 | B3: sábado | C3: 21 | E3: Sorvete
A4: 45599 | B4: domingo
A5: 45600 | B5: segunda-feira | C5: 31 | E5: Corte de Cabelo
A6: 45601 | B6: terça-feira | C6: 500 | D6: 150 | E6: Aluguel / Remuneração Estoque
A7: 45602 | B7: quarta-feira | C7: 5 | D7: 1219 | E7: Bolo / Salário
A8: 45603 | B8: quinta-feira
A9: 45604 | B9: sexta-feira
A10: 45605 | B10: sábado | D10: 20 | E10: Bonificação
A11: 45606 | B11: domingo | C11: 25 | E11: Sorvete
A12: 45607 | B12: segunda-feira | C12: 132 | E12: Ventilador aniversário Mãe
A13: 45608 | B13: terça-feira | C13: 30 | E13: Internet
A14: 45609 | B14: quarta-feira | C14: 90 | D14: 632 | E14: Calça / Adiantamento
A15: 45610 | B15: quinta-feira | C15: 2.5 | E15: Pão de queijo
A16: 45611 | B16: sexta-feira | C16: 10.63 | E16: Uber
A17: 45612 | B17: sábado | D17: 20 | E17: Bonificação
A18: 45613 | B18: domingo | C18: 36 | E18: Sorvete
A19: 45614 | B19: segunda-feira
A20: 45615 | B20: terça-feira | C20: 30.34 | E20: Supermercado
A21: 45616 | B21: quarta-feira | C21: 20 | E21: Crunchyroll
A22: 45617 | B22: quinta-feira
A23: 45618 | B23: sexta-feira
A24: 45619 | B24: sábado | C24: 15.5 | D24: 20 | E24: Mãe (10), Refrigerante / Bonificação
A25: 45620 | B25: domingo | C25: 13.37 | E25: Refrigerante nataly
A26: 45621 | B26: segunda-feira | D26: 778 | E26: 13° salário
A27: 45622 | B27: terça-feira | C27: 96 | E27: Fone, Internet (30), Milshake (26)
A28: 45623 | B28: quarta-feira
A29: 45624 | B29: quinta-feira
A30: 45625 | B30: sexta-feira
A31: 45626 | B31: sábado

Sheet Dezembro
A1: Dia do Mês | B1: Dia da Semana | C1: Despesas | D1: Receitas | E1: Informação adicional | F1: Valor Gasto | G1: Valor Faturado | H1: Saldo
A2: 45627 | B2: Domingo | C2: 127.59 | D2: 0 | E2: Rodízio | F2: =SUM(C2:C31) -> 1497.12 | G2: =SUM(D2:D31) -> 2694 | H2: =G2-F2 -> 1196.88
A3: 45628 | B3: segunda-feira | D3: 1102 | E3: Salário + Bonificação (20)
A4: 45629 | B4: terça-feira
A5: 45630 | B5: quarta-feira
A6: 45631 | B6: quinta-feira | C6: 500 | D6: 150 | E6: Aluguel / Remuneração estoque
A7: 45632 | B7: sexta-feira
A8: 45633 | B8: sábado | C8: 8 | D8: 20 | E8: Lanche / Bonificação (20)
A9: 45634 | B9: domingo
A10: 45635 | B10: segunda-feira | C10: 288.53 | E10: Geladeira, Guarda Roupa, Produtos Rede
A11: 45636 | B11: terça-feira | C11: 8 | E11: Lanche
A12: 45637 | B12: quarta-feira | C12: 23 | D12: 632 | E12: Sorvete / Adiantamento
A13: 45638 | B13: quinta-feira
A14: 45639 | B14: sexta-feira | D14: 20 | E14: Crunchyroll Gustavo
A15: 45640 | B15: sábado | C15: 100 | D15: 20 | E15: Mãe / Bonificação
A16: 45641 | B16: domingo
A17: 45642 | B17: segunda-feira
A18: 45643 | B18: terça-feira
A19: 45644 | B19: quarta-feira
A20: 45645 | B20: quinta-feira
A21: 45646 | B21: sexta-feira | D21: 730 | E21: 13° salário
A22: 45647 | B22: sábado | D22: 20 | E22: Bonificação
A23: 45648 | B23: domingo
A24: 45649 | B24: segunda-feira | C24: 100 | E24: toalha
A25: 45650 | B25: terça-feira | C25: 11 | E25: Lanche
A26: 45651 | B26: quarta-feira
A27: 45652 | B27: quinta-feira | C27: 20 | E27: Crunchyroll
A28: 45653 | B28: sexta-feira | C28: 11 | E28: Lanche
A29: 45654 | B29: sábado | C29: 120 | E29: Mãe (100), jogo mãe
A30: 45655 | B30: domingo | C30: 180 | E30: Kit Churrasco
A31: 45656 | B31: segunda-feira
A32: 45657 | B32: terça-feira

Sheet Total 2025
A1: Janeiro | B1: Pix | C1: Dinheiro F | D1: Cartão | E1: Total | F1: Saldo | H1: Despesa Total 2025 | I1: Receita Total 2025 | J1: Saldo Total 2025
A2: Despesa | B2: =('Janeiro 2025'!H8) -> 1051.37 | C2: =('Janeiro 2025'!I8) -> 325.9 | D2: =('Janeiro 2025'!J8) -> 113.1 | E2: ='Janeiro 2025'!K8 -> 1490.37 | F2: =E3-E2 -> 597.63 | H2: =SUMIF(A2:A46,"Despesa",E2:E46) -> 24611.38 | I2: =SUMIF(A2:A46,"Receita",E2:E46) -> 34480.99 | J2: =SUM(F2:F46) -> 10769.61
A3: Receita | B3: =('Janeiro 2025'!H9) -> 1823 | C3: =('Janeiro 2025'!I9) -> 190 | D3: =('Janeiro 2025'!J9) -> 75 | E3: ='Janeiro 2025'!K9 -> 2088
A5: Fevereiro | B5: Pix | C5: Dinheiro F | D5: Cartão | E5: Total | F5: Saldo
A6: Despesa | B6: =('Fevereiro 2025'!H8) -> 932 | C6: =('Fevereiro 2025'!I8) -> 300.1 | D6: =('Fevereiro 2025'!J8) -> 581.79 | E6: ='Fevereiro 2025'!K8 -> 1813.89 | F6: =E7-E6 -> 4408.11
A7: Receita | B7: =('Fevereiro 2025'!H9) -> 4000 | C7: =('Fevereiro 2025'!I9) -> 330 | D7: =('Fevereiro 2025'!J9) -> 1892 | E7: ='Fevereiro 2025'!K9 -> 6222
A9: Março | B9: Pix | C9: Dinheiro F | D9: Cartão | E9: Total | F9: Saldo
A10: Despesa | B10: =('Março 2025'!H8) -> 952.73 | C10: =('Março 2025'!I8) -> 186 | D10: =('Março 2025'!J8) -> 676.31 | E10: ='Março 2025'!K8 -> 1815.04 | F10: =E11-E10 -> 817.96
A11: Receita | B11: =('Março 2025'!H9) -> 22 | C11: =('Março 2025'!I9) -> 230 | D11: =('Março 2025'!J9) -> 2381 | E11: ='Março 2025'!K9 -> 2633
A13: Abril | B13: Pix | C13: Dinheiro F | D13: Cartão | E13: Total | F13: Saldo
A14: Despesa | B14: =('Abril 2025'!H8) -> 832.98 | C14: =('Abril 2025'!I8) -> 88 | D14: =('Abril 2025'!J8) -> 444.35 | E14: ='Abril 2025'!K8 -> 1365.33 | F14: =E15-E14 -> 1148.67
A15: Receita | B15: =('Abril 2025'!H9) -> 150 | C15: =('Abril 2025'!I9) -> 230 | D15: =('Abril 2025'!J9) -> 2134 | E15: ='Abril 2025'!K9 -> 2514
A17: Maio | B17: Pix | C17: Dinheiro F | D17: Cartão | E17: Total | F17: Saldo
A18: Despesa | B18: =('Maio 2025'!H8) -> 1242.97 | C18: =('Maio 2025'!I8) -> 274.65 | D18: =('Maio 2025'!J8) -> 137.5 | E18: ='Maio 2025'!K8 -> 1655.12 | F18: =E19-E18 -> 673.88
A19: Receita | B19: =('Maio 2025'!H9) -> 0 | C19: =('Maio 2025'!I9) -> 230 | D19: =('Maio 2025'!J9) -> 2099 | E19: ='Maio 2025'!K9 -> 2329
A21: Junho | B21: Pix | C21: Dinheiro F | D21: Cartão | E21: Total | F21: Saldo
A22: Despesa | B22: =('Junho 2025'!H8) -> 4261.98 | C22: =('Junho 2025'!I8) -> 151 | D22: =('Junho 2025'!J8) -> 227.93 | E22: ='Junho 2025'!K8 -> 4640.91 | F22: =E23-E22 -> -2273.91
A23: Receita | B23: =('Junho 2025'!H9) -> 0 | C23: =('Junho 2025'!I9) -> 330 | D23: =('Junho 2025'!J9) -> 2037 | E23: ='Junho 2025'!K9 -> 2367
A25: Julho | B25: Pix | C25: Dinheiro F | D25: Cartão | E25: Total | F25: Saldo
A26: Despesa | B26: =('Julho 2025'!H8) -> 980.15 | C26: =('Julho 2025'!I8) -> 0 | D26: =('Julho 2025'!J8) -> 149.7 | E26: ='Julho 2025'!K8 -> 1129.85 | F26: =E27-E26 -> 8332.94
A27: Receita | B27: =('Julho 2025'!H9) -> 0 | C27: =('Julho 2025'!I9) -> 100 | D27: =('Julho 2025'!J9) -> 9362.79 | E27: ='Julho 2025'!K9 -> 9462.79
A29: Agosto | B29: Pix | C29: Dinheiro F | D29: Cartão | E29: Total | F29: Saldo
A30: Despesa | B30: =('Agosto 2025'!H8) -> 2337.82 | C30: =('Agosto 2025'!I8) -> 68 | D30: =('Agosto 2025'!J8) -> 0 | E30: ='Agosto 2025'!K8 -> 2405.82 | F30: =E31-E30 -> -525.82
A31: Receita | B31: =('Agosto 2025'!H9) -> 0 | C31: =('Agosto 2025'!I9) -> 1880 | D31: =('Agosto 2025'!J9) -> 0 | E31: ='Agosto 2025'!K9 -> 1880
A33: Setembro | B33: Pix | C33: Dinheiro F | D33: Cartão | E33: Total | F33: Saldo
A34: Despesa | B34: =('Setembro 2025'!H8) -> 1472.18 | C34: =('Setembro 2025'!I8) -> 0 | D34: =('Setembro 2025'!J8) -> 240.54 | E34: ='Setembro 2025'!K8 -> 1712.72 | F34: =E35-E34 -> 282.88
A35: Receita | B35: =('Setembro 2025'!H9) -> 50 | C35: =('Setembro 2025'!I9) -> 111.6 | D35: =('Setembro 2025'!J9) -> 1834 | E35: ='Setembro 2025'!K9 -> 1995.6
A37: Outubro | B37: Pix | C37: Dinheiro F | D37: Cartão | E37: Total | F37: Saldo
A38: Despesa | B38: =('Outubro 2025'!H8) -> 2271.3 | C38: =('Outubro 2025'!I8) -> 12 | D38: =('Outubro 2025'!J8) -> 418.56 | E38: =('Outubro 2025'!K8) -> 2701.86 | F38: =E39-E38 -> -723.86
A39: Receita | B39: =('Outubro 2025'!H9) -> 144 | C39: =('Outubro 2025'!I9) -> 0 | D39: =('Outubro 2025'!J9) -> 1834 | E39: =('Outubro 2025'!K9) -> 1978
A41: Novembro | B41: Pix | C41: Dinheiro F | D41: Cartão | E41: Total | F41: Saldo
A42: Despesa | B42: =('Novembro 2025'!H8) -> 1366.41 | C42: =('Novembro 2025'!I8) -> 0 | D42: =('Novembro 2025'!J8) -> 689.13 | E42: =('Novembro 2025'!K8) -> 2055.54 | F42: =E43-E42 -> -1043.94
A43: Receita | B43: =('Novembro 2025'!H9) -> 900 | C43: =('Novembro 2025'!I9) -> 111.6 | D43: =('Novembro 2025'!J9) -> 0 | E43: =('Novembro 2025'!K9) -> 1011.6
A45: Dezembro | B45: Pix | C45: Dinheiro F | D45: Cartão | E45: Total | F45: Saldo
A46: Despesa | B46: =('Dezembro 2025'!H8) -> 1764.07 | C46: =('Dezembro 2025'!I8) -> 0 | D46: =('Dezembro 2025'!J8) -> 60.86 | E46: =('Dezembro 2025'!K8) -> 1824.93 | F46: =E47-E46 -> -924.93
A47: Receita | B47: =('Dezembro 2025'!H9) -> 900 | C47: =('Dezembro 2025'!I9) -> 0 | D47: =('Dezembro 2025'!J9) -> 0 | E47: =('Dezembro 2025'!K9) -> 900

Sheet Janeiro 2026
A6: Semana 1 | J6: Semana 2
A7: Janeiro | J7: Janeiro
A8: 46023 | B8: - | C8: - | D8: - | E8: - | F8: - | G8: - | H8: Saldo da semana | J8: 46030 | K8: - | L8: - | M8: - | N8: - | O8: - | P8: - | Q8: Saldo da semana | S8: =SUM(B8:D14) -> 467.82 | T8: =SUM(E8:G14) -> 0
A9: 46024 | B9: - | C9: - | D9: - | E9: - | F9: - | G9: - | H9: =T8-S8 -> -467.82 | J9: 46031 | K9: - | L9: - | M9: - | N9: - | O9: - | P9: - | Q9: =T9-S9 -> -441.98 | S9: =SUM(K8:M14) -> 441.98 | T9: =sum(N8:P14) -> 0
A10: 46025 | B10: 22.1 | C10: 34.9 | D10: 26.1 | E10: - | F10: - | G10: - | J10: 46032 | K10: - | L10: - | M10: - | N10: - | O10: - | P10: - | S10: =sum(B18:D24) -> 1147.06 | T10: =sum(E18:G24) -> 100
A11: 46026 | B11: - | C11: - | D11: - | E11: - | F11: - | G11: - | J11: 46033 | K11: - | L11: - | M11: - | N11: - | O11: - | P11: - | S11: =sum(K18:M24) -> 0 | T11: =sum(N18:P24) -> 0
A12: 46027 | B12: - | C12: - | D12: - | E12: - | F12: - | G12: - | J12: 46034 | K12: 340 | L12: - | M12: - | N12: - | O12: - | P12: - | S12: =sum(B29:D31) -> 32.35 | T12: =sum(E29:G31) -> 223.2
A13: 46028 | B13: 384.72 | C13: - | D13: - | E13: - | F13: - | G13: - | J13: 46035 | K13: 10 | L13: - | M13: - | N13: - | O13: - | P13: -
A14: 46029 | B14: - | C14: - | D14: - | E14: - | F14: - | G14: - | J14: 46036 | K14: 57.98 | L14: 34 | M14: - | N14: - | O14: - | P14: -
A16: Semana 3 | J16: Semana 4
A17: Janeiro | J17: Janeiro
A18: 46037 | B18: - | C18: - | D18: - | E18: - | F18: - | G18: - | H18: Saldo da semana | J18: 46044 | K18: - | L18: - | M18: - | N18: - | O18: - | P18: - | Q18: Saldo da semana
A19: 46038 | B19: 40 | C19: - | D19: - | E19: - | F19: - | G19: - | H19: =T10-S10 -> -1047.06 | J19: 46045 | K19: - | L19: - | M19: - | N19: - | O19: - | P19: - | Q19: =T11-S11 -> 0
A20: 46039 | B20: - | C20: - | D20: - | E20: - | F20: - | G20: - | J20: 46046 | K20: - | L20: - | M20: - | N20: - | O20: - | P20: -
A21: 46040 | B21: - | C21: - | D21: - | E21: - | F21: - | G21: - | J21: 46047 | K21: - | L21: - | M21: - | N21: - | O21: - | P21: -
A22: 46041 | B22: 10.4 | C22: 375 | D22: 100 | E22: - | F22: - | G22: - | J22: 46048 | K22: - | L22: - | M22: - | N22: - | O22: - | P22: -
A23: 46042 | B23: 500 | C23: - | D23: - | E23: - | F23: - | G23: - | J23: 46049 | K23: - | L23: - | M23: - | N23: - | O23: - | P23: -
A24: 46043 | B24: 70 | C24: 36.9 | D24: 14.76 | E24: 100 | F24: - | G24: - | J24: 46050 | K24: - | L24: - | M24: - | N24: - | O24: - | P24: -
A27: Semana 5 | J27: Saldo Geral
A28: Janeiro | J28: =sum(H9,H19,H30,Q19,Q9) -> -1766.01
A29: 46051 | B29: - | C29: - | D29: - | E29: - | F29: - | G29: - | H29: Saldo da semana
A30: 46052 | B30: 9.69 | C30: - | D30: - | E30: 111.6 | F30: - | G30: - | H30: =T12-S12 -> 190.85
A31: 46053 | B31: 22.66 | C31: - | D31: - | E31: 111.6 | F31: - | G31: -

Sheet Fevereiro 2026
A6: Semana 1 | J6: Semana 2
A7: Fevereiro | J7: Fevereiro
A8: 46054 | B8: - | C8: - | D8: - | E8: - | F8: - | G8: - | H8: Saldo da semana | J8: 46061 | K8: - | L8: - | M8: - | N8: - | O8: - | P8: - | Q8: Saldo da semana | S8: =SUM(B8:D14) -> 390 | T8: =SUM(E8:G14) -> 0
A9: 46055 | B9: 390 | C9: - | D9: - | E9: - | F9: - | G9: - | H9: =T8-S8 -> -390 | J9: 46062 | K9: 384.72 | L9: 27.98 | M9: - | N9: - | O9: - | P9: - | Q9: =T9-S9 -> -543.19 | S9: =SUM(K8:M14) -> 543.19 | T9: =sum(N8:P14) -> 0
A10: 46056 | B10: - | C10: - | D10: - | E10: - | F10: - | G10: - | J10: 46063 | K10: - | L10: - | M10: - | N10: - | O10: - | P10: - | S10: =sum(B18:D24) -> 183.01 | T10: =sum(E18:G24) -> 0
A11: 46057 | B11: - | C11: - | D11: - | E11: - | F11: - | G11: - | J11: 46064 | K11: - | L11: - | M11: - | N11: - | O11: - | P11: - | S11: =sum(K18:M24) -> 125.06 | T11: =sum(N18:P24) -> 0
A12: 46058 | B12: - | C12: - | D12: - | E12: - | F12: - | G12: - | J12: 46065 | L12: - | M12: - | N12: - | O12: - | P12: - | S12: =sum(B29:D31) -> 0 | T12: =sum(E29:G31) -> 0
A13: 46059 | B13: - | C13: - | D13: - | E13: - | F13: - | G13: - | J13: 46066 | K13: 70 | L13: 12.69 | M13: 47.8 | N13: - | O13: - | P13: -
A14: 46060 | B14: - | C14: - | D14: - | E14: - | F14: - | G14: - | J14: 46067 | K14: - | L14: - | M14: - | N14: - | O14: - | P14: -
A16: Semana 3 | J16: Semana 4
A17: Fevereiro | J17: Fevereiro
A18: 46068 | B18: - | C18: - | D18: - | E18: - | F18: - | G18: - | H18: Saldo da semana | J18: 46075 | K18: - | L18: - | M18: - | N18: - | O18: - | P18: - | Q18: Saldo da semana
A19: 46069 | B19: - | C19: - | D19: - | E19: - | F19: - | G19: - | H19: =T10-S10 -> -183.01 | J19: 46076 | K19: - | L19: - | M19: - | N19: - | O19: - | P19: - | Q19: =T11-S11 -> -125.06
A20: 46070 | B20: - | C20: - | D20: - | E20: - | F20: - | G20: - | J20: 46077 | K20: - | L20: - | M20: - | N20: - | O20: - | P20: -
A21: 46071 | B21: - | C21: - | D21: - | E21: - | F21: - | G21: - | J21: 46078 | K21: - | L21: - | M21: - | N21: - | O21: - | P21: -
A22: 46072 | B22: 145.01 | C22: - | D22: - | E22: - | F22: - | G22: - | J22: 46079 | K22: 20 | L22: 50 | M22: - | N22: - | O22: - | P22: -
A23: 46073 | B23: 38 | C23: - | D23: - | E23: - | F23: - | G23: - | J23: 46080 | K23: 3.66 | L23: - | M23: - | N23: - | O23: - | P23: -
A24: 46074 | B24: - | C24: - | D24: - | E24: - | F24: - | G24: - | J24: 46081 | K24: 51.4 | L24: - | M24: - | N24: - | O24: - | P24: -
J27: Saldo Geral
J28: =sum(H9,H19,H30,Q19,Q9) -> -1241.26

Sheet Março 2026
A6: Semana 1 | J6: Semana 2
A7: Março | J7: Março
A8: 46082 | B8: - | C8: - | D8: - | E8: - | F8: - | G8: - | H8: Saldo da semana | J8: 46089 | K8: - | L8: - | M8: - | N8: - | O8: - | P8: - | Q8: Saldo da semana | S8: =SUM(B8:D14) -> 404 | T8: =SUM(E8:G14) -> 200
A9: 46083 | B9: 375 | C9: - | D9: - | E9: - | F9: - | G9: - | H9: =T8-S8 -> -204 | J9: 46090 | K9: 79.99 | L9: 384.72 | M9: - | N9: - | O9: - | P9: - | Q9: =T9-S9 -> -469.71 | S9: =SUM(K8:M14) -> 469.71 | T9: =sum(N8:P14) -> 0
A10: 46084 | B10: - | C10: - | D10: - | E10: - | F10: - | G10: - | J10: 46091 | K10: - | L10: - | M10: - | N10: - | O10: - | P10: - | S10: =sum(B18:D24) -> 436.46 | T10: =sum(E18:G24) -> 0
A11: 46085 | B11: - | C11: - | D11: - | E11: - | F11: - | G11: - | J11: 46092 | K11: - | L11: - | M11: - | N11: - | O11: - | P11: - | S11: =sum(K18:M24) -> 199.8 | T11: =sum(N18:P24) -> 0
A12: 46086 | B12: 20 | C12: - | D12: - | E12: - | F12: - | G12: - | J12: 46093 | K12: - | L12: - | M12: - | N12: - | O12: - | P12: - | S12: =sum(B29:D31) -> 80 | T12: =sum(E29:G31) -> 0
A13: 46087 | B13: 9 | C13: - | D13: - | E13: 200 | F13: - | G13: - | J13: 46094 | K13: - | L13: - | M13: - | N13: - | O13: - | P13: -
A14: 46088 | B14: - | C14: - | D14: - | E14: - | F14: - | G14: - | J14: 46095 | K14: 5 | L14: - | M14: - | N14: - | O14: - | P14: -
A16: Semana 3 | J16: Semana 4
A17: Março | J17: Março
A18: 46096 | B18: - | C18: - | D18: - | E18: - | F18: - | G18: - | H18: Saldo da semana | J18: 46103 | K18: - | L18: - | M18: - | N18: - | O18: - | P18: - | Q18: Saldo da semana
A19: 46097 | B19: 260 | C19: - | D19: - | E19: - | F19: - | G19: - | H19: =T10-S10 -> -436.46 | J19: 46104 | K19: 67.1 | L19: - | M19: - | N19: - | O19: - | P19: - | Q19: =T11-S11 -> -199.8
A20: 46098 | B20: 3.76 | C20: 130 | D20: - | E20: - | F20: - | G20: - | J20: 46105 | K20: 40.7 | L20: - | M20: - | N20: - | O20: - | P20: -
A21: 46099 | B21: 3.92 | C21: - | D21: - | E21: - | F21: - | G21: - | J21: 46106 | K21: 72 | L21: - | M21: - | N21: - | O21: - | P21: -
A22: 46100 | B22: 38.78 | C22: - | D22: - | E22: - | F22: - | G22: - | J22: 46107 | K22: - | L22: - | M22: - | N22: - | O22: - | P22: -
A23: 46101 | B23: - | C23: - | D23: - | E23: - | F23: - | G23: - | J23: 46108 | K23: 20 | L23: - | M23: - | N23: - | O23: - | P23: -
A24: 46102 | B24: - | C24: - | D24: - | E24: - | F24: - | G24: - | J24: 46109 | K24: - | L24: - | M24: - | N24: - | O24: - | P24: -
A27: Semana 5 | J27: Saldo Geral
A28: Março | J28: =sum(H9,H19,H30,Q19,Q9) -> -1389.97
A29: 46110 | B29: 30 | C29: - | D29: - | E29: - | F29: - | G29: - | H29: Saldo da semana
A30: 46111 | B30: 50 | C30: - | D30: - | E30: - | F30: - | G30: - | H30: =T12-S12 -> -80
A31: 46112 | B31: - | C31: - | D31: - | E31: - | F31: - | G31: -

Sheet Abril 2026
A6: Semana 1 | J6: Semana 2
A7: Abril | J7: Abril
A8: 46113 | B8: 3.84 | C8: - | D8: - | E8: - | F8: - | G8: - | H8: Saldo da semana | J8: 46120 | K8: 5.5 | L8: - | M8: - | N8: - | O8: - | P8: - | Q8: Saldo da semana | S8: =SUM(B8:D14) -> 536.95 | T8: =SUM(E8:G14) -> 150
A9: 46114 | B9: - | C9: - | D9: - | E9: - | F9: - | G9: - | H9: =T8-S8 -> -386.95 | J9: 46121 | K9: 126.25 | L9: - | M9: - | N9: - | O9: - | P9: - | Q9: =T9-S9 -> -391.08 | S9: =SUM(K8:M14) -> 406.08 | T9: =sum(N8:P14) -> 15
A10: 46115 | B10: - | C10: - | D10: - | E10: - | F10: - | G10: - | J10: 46122 | K10: 129.24 | L10: - | M10: - | N10: - | O10: - | P10: - | S10: =sum(B18:D24) -> 562.75 | T10: =sum(E18:G24) -> 0
A11: 46116 | B11: - | C11: - | D11: - | E11: - | F11: - | G11: - | J11: 46123 | K11: - | L11: - | M11: - | N11: - | O11: - | P11: - | S11: =sum(K18:M24) -> 130.61 | T11: =sum(N18:P24) -> 0
A12: 46117 | B12: - | C12: - | D12: - | E12: - | F12: - | G12: - | J12: 46124 | K12: 55.09 | L12: - | M12: - | N12: 15 | O12: - | P12: - | S12: =sum(B29:D30) -> 53.76 | T12: =sum(E29:G30) -> 300
A13: 46118 | B13: 80 | C13: - | D13: - | E13: 150 | F13: - | G13: - | J13: 46125 | K13: 40 | L13: - | M13: - | N13: - | O13: - | P13: -
A14: 46119 | B14: 384.72 | C14: 62.89 | D14: 5.5 | E14: - | F14: - | G14: - | J14: 46126 | K14: 50 | L14: - | M14: - | N14: - | O14: - | P14: -
A16: Semana 3 | J16: Semana 4
A17: Abril | J17: Abril
A18: 46127 | B18: 12.75 | C18: - | D18: - | E18: - | F18: - | G18: - | H18: Saldo da semana | J18: 46134 | K18: 26.77 | L18: - | M18: - | N18: - | O18: - | P18: - | Q18: Saldo da semana
A19: 46128 | B19: 50 | C19: - | D19: - | E19: - | F19: - | G19: - | H19: =T10-S10 -> -562.75 | J19: 46135 | K19: - | L19: - | M19: - | N19: - | O19: - | P19: - | Q19: =T11-S11 -> -130.61
A20: 46129 | B20: - | C20: - | D20: - | E20: - | F20: - | G20: - | J20: 46136 | K20: - | L20: - | M20: - | N20: - | O20: - | P20: -
A21: 46130 | B21: - | C21: - | D21: - | E21: - | F21: - | G21: - | J21: 46137 | K21: 100 | L21: - | M21: - | N21: - | O21: - | P21: -
A22: 46131 | B22: - | C22: - | D22: - | E22: - | F22: - | G22: - | J22: 46138 | K22: - | L22: - | M22: - | N22: - | O22: - | P22: -
A23: 46132 | B23: 500 | C23: - | D23: - | E23: - | F23: - | G23: - | J23: 46139 | K23: - | L23: - | M23: - | N23: - | O23: - | P23: -
A24: 46133 | B24: - | C24: - | D24: - | E24: - | F24: - | G24: - | J24: 46140 | K24: 3.84 | L24: - | M24: - | N24: - | O24: - | P24: -
A27: Semana 5 | J27: Saldo Geral
A28: Abril | J28: =sum(H9,H19,H30,Q19,Q9) -> -1225.15
A29: 46141 | B29: 50 | C29: 3.76 | D29: - | E29: 300 | F29: - | G29: - | H29: Saldo da semana
A30: 46142 | B30: - | C30: - | D30: - | E30: - | F30: - | G30: - | H30: =T12-S12 -> 246.24

Sheet Maio 2026
A6: Semana 1 | J6: Semana 2
A7: Maio | J7: Maio
A8: 46143 | B8: - | C8: - | D8: - | E8: - | F8: - | G8: - | H8: Saldo da semana | J8: 46150 | K8: - | L8: - | M8: - | N8: - | O8: - | P8: - | Q8: Saldo da semana | S8: =SUM(B8:D14) -> 0 | T8: =SUM(E8:G14) -> 0
A9: 46144 | B9: - | C9: - | D9: - | E9: - | F9: - | G9: - | H9: =T8-S8 -> 0 | J9: 46151 | K9: - | L9: - | M9: - | N9: - | O9: - | P9: - | Q9: =T9-S9 -> -423.11 | S9: =SUM(K8:M14) -> 423.11 | T9: =sum(N8:P14) -> 0
A10: 46145 | B10: - | C10: - | D10: - | E10: - | F10: - | G10: - | J10: 46152 | K10: 384.72 | L10: - | M10: - | N10: - | O10: - | P10: - | S10: =sum(B18:D24) -> 761.38 | T10: =sum(E18:G24) -> 30
A11: 46146 | B11: - | C11: - | D11: - | E11: - | F11: - | G11: - | J11: 46153 | K11: 32.89 | L11: - | M11: - | N11: - | O11: - | P11: - | S11: =sum(K18:M24) -> 159.99 | T11: =sum(N18:P24) -> 5.9
A12: 46147 | B12: - | C12: - | D12: - | E12: - | F12: - | G12: - | J12: 46154 | K12: 5.5 | L12: - | M12: - | N12: - | O12: - | P12: - | S12: =sum(B29:D31) -> 0 | T12: =sum(E29:G31) -> 0
A13: 46148 | B13: - | C13: - | D13: - | E13: - | F13: - | G13: - | J13: 46155 | K13: - | L13: - | M13: - | N13: - | O13: - | P13: -
A14: 46149 | B14: - | C14: - | D14: - | E14: - | F14: - | G14: - | J14: 46156 | K14: - | L14: - | M14: - | N14: - | O14: - | P14: -
A16: Semana 3 | J16: Semana 4
A17: Maio | J17: Maio
A18: 46157 | B18: - | C18: - | D18: - | E18: - | F18: - | G18: - | H18: Saldo da semana | J18: 46164 | K18: - | L18: - | M18: - | N18: - | O18: - | P18: - | Q18: Saldo da semana
A19: 46158 | B19: - | C19: - | D19: - | E19: - | F19: - | G19: - | H19: =T10-S10 -> -731.38 | J19: 46165 | K19: - | L19: - | M19: - | N19: - | O19: - | P19: - | Q19: =T11-S11 -> -154.09
A20: 46159 | B20: 59.57 | C20: - | D20: - | E20: - | F20: - | G20: - | J20: 46166 | K20: - | L20: - | M20: - | N20: - | O20: - | P20: -
A21: 46160 | B21: 20 | C21: 34 | D21: - | E21: - | F21: - | G21: - | J21: 46167 | K21: - | L21: - | M21: - | N21: - | O21: - | P21: -
A22: 46161 | B22: 8.6 | C22: - | D22: - | E22: - | F22: - | G22: - | J22: 46168 | K22: 100 | L22: 50 | M22: - | N22: - | O22: - | P22: -
A23: 46162 | B23: 474 | C23: 20.97 | D23: 4.24 | E23: - | F23: - | G23: - | J23: 46169 | K23: 4 | L23: - | M23: - | N23: - | O23: - | P23: -
A24: 46163 | B24: 140 | C24: - | D24: - | E24: 30 | F24: - | G24: - | J24: 46170 | K24: 5.99 | L24: - | M24: - | N24: 5.9 | O24: - | P24: -
A27: Semana 5 | J27: Saldo Geral
A28: Maio | J28: =sum(H9,H19,H30,Q19,Q9) -> -1308.58
A29: 46171 | B29: - | C29: - | D29: - | E29: - | F29: - | G29: - | H29: Saldo da semana
A30: 46172 | B30: - | C30: - | D30: - | E30: - | F30: - | G30: - | H30: =T12-S12 -> 0
A31: 46173 | B31: - | C31: - | D31: - | E31: - | F31: - | G31: -

Sheet Junho 2026
A6: Semana 1 | J6: Semana 2
A7: Junho | J7: Junho
A8: 46174 | B8: 10.75 | C8: - | D8: - | E8: 24 | F8: - | G8: - | H8: Saldo da semana | J8: 46181 | K8: - | L8: - | M8: - | N8: - | O8: - | P8: - | Q8: Saldo da semana | S8: =SUM(B8:D14) -> 176.1 | T8: =SUM(E8:G14) -> 71.08
A9: 46175 | B9: - | C9: - | D9: - | E9: - | F9: - | G9: - | H9: =T8-S8 -> -105.02 | J9: 46182 | K9: - | L9: - | M9: - | N9: - | O9: - | P9: - | Q9: =T9-S9 -> 0 | S9: =SUM(K8:M14) -> 0 | T9: =sum(N8:P14) -> 0
A10: 46176 | B10: 50 | C10: - | D10: - | E10: - | F10: - | G10: - | J10: 46183 | K10: - | L10: - | M10: - | N10: - | O10: - | P10: - | S10: =sum(B18:D24) -> 0 | T10: =sum(E18:G24) -> 0
A11: 46177 | B11: 115.35 | C11: - | D11: - | E11: 15.08 | F11: - | G11: - | J11: 46184 | K11: - | L11: - | M11: - | N11: - | O11: - | P11: - | S11: =sum(K18:M24) -> 0 | T11: =sum(N18:P24) -> 0
A12: 46178 | B12: - | C12: - | D12: - | E12: - | F12: - | G12: - | J12: 46185 | K12: - | L12: - | M12: - | N12: - | O12: - | P12: - | S12: =sum(B29:D30) -> 0 | T12: =sum(E29:G30) -> 0
A13: 46179 | B13: - | C13: - | D13: - | E13: 32 | F13: - | G13: - | J13: 46186 | K13: - | L13: - | M13: - | N13: - | O13: - | P13: -
A14: 46180 | B14: - | C14: - | D14: - | E14: - | F14: - | G14: - | J14: 46187 | K14: - | L14: - | M14: - | N14: - | O14: - | P14: -
A16: Semana 3 | J16: Semana 4
A17: Junho | J17: Junho
A18: 46188 | B18: - | C18: - | D18: - | E18: - | F18: - | G18: - | H18: Saldo da semana | J18: 46195 | K18: - | L18: - | M18: - | N18: - | O18: - | P18: - | Q18: Saldo da semana
A19: 46189 | B19: - | C19: - | D19: - | E19: - | F19: - | G19: - | H19: =T10-S10 -> 0 | J19: 46196 | K19: - | L19: - | M19: - | N19: - | O19: - | P19: - | Q19: =T11-S11 -> 0
A20: 46190 | B20: - | C20: - | D20: - | E20: - | F20: - | G20: - | J20: 46197 | K20: - | L20: - | M20: - | N20: - | O20: - | P20: -
A21: 46191 | B21: - | C21: - | D21: - | E21: - | F21: - | G21: - | J21: 46198 | K21: - | L21: - | M21: - | N21: - | O21: - | P21: -
A22: 46192 | B22: - | C22: - | D22: - | E22: - | F22: - | G22: - | J22: 46199 | K22: - | L22: - | M22: - | N22: - | O22: - | P22: -
A23: 46193 | B23: - | C23: - | D23: - | E23: - | F23: - | G23: - | J23: 46200 | K23: - | L23: - | M23: - | N23: - | O23: - | P23: -
A24: 46194 | B24: - | C24: - | D24: - | E24: - | F24: - | G24: - | J24: 46201 | K24: - | L24: - | M24: - | N24: - | O24: - | P24: -
A27: Semana 5 | J27: Saldo Geral
A28: Junho | J28: =sum(H9,H19,H30,Q19,Q9) -> -105.02
A29: 46202 | B29: - | C29: - | D29: - | E29: - | F29: - | G29: - | H29: Saldo da semana
A30: 46203 | B30: - | C30: - | D30: - | E30: - | F30: - | G30: - | H30: =T12-S12 -> 0

Sheet Julho 2026
A6: Semana 1 | J6: Semana 2
A7: Junho | J7: Junho
A8: 46174 | B8: - | C8: - | D8: - | E8: - | F8: - | G8: - | H8: Saldo da semana | J8: 46030 | K8: - | L8: - | M8: - | N8: - | O8: - | P8: - | Q8: Saldo da semana | S8: =SUM(B8:D14) -> 0 | T8: =SUM(E8:G14) -> 0
A9: 46175 | B9: - | C9: - | D9: - | E9: - | F9: - | G9: - | H9: =T8-S8 -> 0 | J9: 46031 | K9: - | L9: - | M9: - | N9: - | O9: - | P9: - | Q9: =T9-S9 -> 0 | S9: =SUM(K8:M14) -> 0 | T9: =sum(N8:P14) -> 0
A10: 46176 | B10: - | C10: - | D10: - | E10: - | F10: - | G10: - | J10: 46032 | K10: - | L10: - | M10: - | N10: - | O10: - | P10: - | S10: =sum(B18:D24) -> 0 | T10: =sum(E18:G24) -> 0
A11: 46177 | B11: - | C11: - | D11: - | E11: - | F11: - | G11: - | J11: 46033 | K11: - | L11: - | M11: - | N11: - | O11: - | P11: - | S11: =sum(K18:M24) -> 0 | T11: =sum(N18:P24) -> 0
A12: 46178 | B12: - | C12: - | D12: - | E12: - | F12: - | G12: - | J12: 46034 | K12: - | L12: - | M12: - | N12: - | O12: - | P12: - | S12: =sum(B29:D31) -> 0 | T12: =sum(E29:G31) -> 0
A13: 46179 | B13: - | C13: - | D13: - | E13: - | F13: - | G13: - | J13: 46035 | K13: - | L13: - | M13: - | N13: - | O13: - | P13: -
A14: 46180 | B14: - | C14: - | D14: - | E14: - | F14: - | G14: - | J14: 46036 | K14: - | L14: - | M14: - | N14: - | O14: - | P14: -
A16: Semana 3 | J16: Semana 4
A17: Junho | J17: Junho
A18: 46037 | B18: - | C18: - | D18: - | E18: - | F18: - | G18: - | H18: Saldo da semana | J18: 46044 | K18: - | L18: - | M18: - | N18: - | O18: - | P18: - | Q18: Saldo da semana
A19: 46038 | B19: - | C19: - | D19: - | E19: - | F19: - | G19: - | H19: =T10-S10 -> 0 | J19: 46045 | K19: - | L19: - | M19: - | N19: - | O19: - | P19: - | Q19: =T11-S11 -> 0
A20: 46039 | B20: - | C20: - | D20: - | E20: - | F20: - | G20: - | J20: 46046 | K20: - | L20: - | M20: - | N20: - | O20: - | P20: -
A21: 46040 | B21: - | C21: - | D21: - | E21: - | F21: - | G21: - | J21: 46047 | K21: - | L21: - | M21: - | N21: - | O21: - | P21: -
A22: 46041 | B22: - | C22: - | D22: - | E22: - | F22: - | G22: - | J22: 46048 | K22: - | L22: - | M22: - | N22: - | O22: - | P22: -
A23: 46042 | B23: - | C23: - | D23: - | E23: - | F23: - | G23: - | J23: 46049 | K23: - | L23: - | M23: - | N23: - | O23: - | P23: -
A24: 46043 | B24: - | C24: - | D24: - | E24: - | F24: - | G24: - | J24: 46050 | K24: - | L24: - | M24: - | N24: - | O24: - | P24: -
A27: Semana 5 | J27: Saldo Geral
A28: Junho | J28: =sum(H9,H19,H30,Q19,Q9) -> 0
A29: 46051 | B29: - | C29: - | D29: - | E29: - | F29: - | G29: - | H29: Saldo da semana
A30: 46052 | B30: - | C30: - | D30: - | E30: - | F30: - | G30: - | H30: =T12-S12 -> 0
A31: 46053 | B31: - | C31: - | D31: - | E31: - | F31: - | G31: -

Sheet Abril 2025
A6: Mês | B6: Semana | C6: Saida | D6: Meio | E6: Informação | M6: Mês | N6: Semana | O6: Entrada | P6: Meio | Q6: Informação
A7: 45748 | B7: Terça-feira | C7: - | D7: - | E7: - | G7: =K9-K8 -> 1148.67 | H7: Pix | I7: Dinheiro F | J7: Cartão | K7: Total | M7: 45748 | N7: Terça-feira | O7: - | P7: - | Q7: -
A8: 45749 | B8: quarta-feira | C8: 132.98 | D8: Pix | E8: Presente Gustavo | G8: Despesas | H8: =SUMIF(D7:D41,"Pix",C7:C41) -> 832.98 | I8: =SUMIF(D7:D41,"Dinheiro F",C7:C41) -> 88 | J8: =SUMIF(D7:D41,"Cartão",C7:C41) -> 444.35 | K8: =SUM(H8:J8) -> 1365.33 | M8: 45749 | N8: quarta-feira | O8: - | P8: - | Q8: -
A9: 45750 | B9: quinta-feira | C9: 49.98 | D9: Cartão | E9: Calça Moletom | G9: Receita | H9: =SUMIF(P7:P41,"Pix",O7:O41) -> 150 | I9: =SUMIF(P7:P41,"Dinheiro F",O7:O41) -> 230 | J9: =SUMIF(P7:P41,"Cartão",O7:O41) -> 2134 | K9: =SUM(H9:J9) -> 2514 | M9: 45750 | N9: quinta-feira | O9: 150 | P9: Dinheiro F | Q9: Estoque
A10: 45751 | B10: sexta-feira | C10: - | D10: - | E10: - | M10: 45751 | N10: sexta-feira | O10: 150 | P10: Pix | Q10: Limpeza Marquize
A11: 45752 | B11: sábado | C11: 37.99 | D11: Cartão | E11: Camisa Uv | M11: 45752 | N11: sábado | O11: 20 | P11: Dinheiro F | Q11: Bonificação
A12: 45753 | B12: domingo | C12: 500 | D12: Pix | E12: Aluguel | M12: 45753 | N12: domingo | O12: - | P12: - | Q12: -
A13: 45753 | B13: domingo | C13: 23.18 | D13: Cartão | E13: Sorvete Mãe | M13: 45753 | N13: domingo | O13: - | P13: - | Q13: -
A14: 45754 | B14: segunda-feira | C14: - | D14: - | E14: - | M14: 45754 | N14: segunda-feira | O14: - | P14: - | Q14: -
A15: 45755 | B15: terça-feira | C15: - | D15: - | E15: - | M15: 45755 | N15: terça-feira | O15: - | P15: - | Q15: -
A16: 45756 | B16: quarta-feira | C16: - | D16: - | E16: - | M16: 45756 | N16: quarta-feira | O16: - | P16: - | Q16: -
A17: 45757 | B17: quinta-feira | C17: - | D17: - | E17: - | M17: 45757 | N17: quinta-feira | O17: - | P17: - | Q17: -
A18: 45758 | B18: sexta-feira | C18: - | D18: - | E18: - | M18: 45758 | N18: sexta-feira | O18: - | P18: - | Q18: -
A19: 45759 | B19: sábado | C19: 62 | D19: Cartão | E19: Uber Gustavo | M19: 45759 | N19: sábado | O19: 20 | P19: Dinheiro F | Q19: Bonificação
A20: 45759 | B20: sábado | C20: 100 | D20: Pix | E20: Pizza (Mãe) | M20: 45759 | N20: sábado | O20: - | P20: - | Q20: -
A21: 45760 | B21: domingo | C21: 43.32 | D21: Cartão | E21: Sorvete | M21: 45760 | N21: domingo | O21: - | P21: - | Q21: -
A22: 45761 | B22: segunda-feira | C22: - | D22: - | E22: - | M22: 45761 | N22: segunda-feira | O22: - | P22: - | Q22: -
A23: 45762 | B23: terça-feira | C23: - | D23: - | E23: - | M23: 45762 | N23: terça-feira | O23: - | P23: - | Q23: -
A24: 45763 | B24: quarta-feira | C24: 18.5 | D24: Dinheiro F | E24: Lanches | M24: 45763 | N24: quarta-feira | O24: 632 | P24: Cartão | Q24: Adiantamento
A25: 45764 | B25: quinta-feira | C25: - | D25: - | E25: - | M25: 45764 | N25: quinta-feira | O25: - | P25: - | Q25: -
A26: 45765 | B26: sexta-feira | C26: 47 | D26: Dinheiro F | E26: Sorvete | M26: 45765 | N26: sexta-feira | O26: - | P26: - | Q26: -
A27: 45766 | B27: sábado | C27: - | D27: - | E27: - | M27: 45766 | N27: sábado | O27: 20 | P27: Dinheiro F | Q27: Bonificação
A28: 45767 | B28: domingo | C28: - | D28: - | E28: - | M28: 45767 | N28: domingo | O28: - | P28: - | Q28: -
A29: 45768 | B29: segunda-feira | C29: 50.95 | D29: Cartão | E29: Chocolates | M29: 45768 | N29: segunda-feira | O29: - | P29: - | Q29: -
A30: 45769 | B30: terça-feira | C30: 14 | D30: Dinheiro F | E30: Lanches | M30: 45769 | N30: terça-feira | O30: - | P30: - | Q30: -
A31: 45770 | B31: quarta-feira | C31: 107 | D31: Cartão | E31: Geladeira | M31: 45770 | N31: quarta-feira | O31: - | P31: - | Q31: -
A32: 45771 | B32: quinta-feira | C32: 50 | D32: Pix | E32: Mãe | M32: 45771 | N32: quinta-feira | O32: - | P32: - | Q32: -
A33: 45772 | B33: sexta-feira | C33: - | D33: - | E33: - | M33: 45772 | N33: sexta-feira | O33: - | P33: - | Q33: -
A34: 45773 | B34: sábado | C34: 8.5 | D34: Dinheiro F | E34: Lanches | M34: 45773 | N34: sábado | O34: 20 | P34: Dinheiro F | Q34: Bonificação
A35: 45774 | B35: domingo | C35: 55.79 | D35: Cartão | E35: Sorvete | M35: 45774 | N35: domingo | O35: - | P35: - | Q35: -
A36: 45775 | B36: segunda-feira | C36: - | D36: - | E36: - | M36: 45775 | N36: segunda-feira | O36: - | P36: - | Q36: -
A37: 45776 | B37: terça-feira | C37: 14.14 | D37: Cartão | E37: Pão e Forma e suco | M37: 45776 | N37: terça-feira | O37: 1502 | P37: Cartão | Q37: Salário
A38: 45777 | B38: quarta-feira | C38: 50 | D38: Pix | E38: Mãe | M38: 45777 | N38: quarta-feira | O38: - | P38: - | Q38: -

Sheet Maio 2025
A6: Mês | B6: Semana | C6: Saida | D6: Meio | E6: Informação | M6: Mês | N6: Semana | O6: Entrada | P6: Meio | Q6: Informação
A7: 45778 | B7: Quinta-feira | C7: - | D7: - | E7: - | G7: =K9-K8 -> 673.88 | H7: Pix | I7: Dinheiro F | J7: Cartão | K7: Total | M7: 45778 | N7: Quinta-feira | O7: - | P7: - | Q7: -
A8: 45779 | B8: sexta-feira | C8: - | D8: - | E8: - | G8: Despesas | H8: =SUMIF(D7:D41,"Pix",C7:C41) -> 1242.97 | I8: =SUMIF(D7:D41,"Dinheiro F",C7:C41) -> 274.65 | J8: =SUMIF(D7:D41,"Cartão",C7:C41) -> 137.5 | K8: =SUM(H8:J8) -> 1655.12 | M8: 45779 | N8: sexta-feira | O8: - | P8: - | Q8: -
A9: 45780 | B9: sábado | C9: - | D9: - | E9: - | G9: Receita | H9: =SUMIF(P7:P41,"Pix",O7:O41) -> 0 | I9: =SUMIF(P7:P41,"Dinheiro F",O7:O41) -> 230 | J9: =SUMIF(P7:P41,"Cartão",O7:O41) -> 2099 | K9: =SUM(H9:J9) -> 2329 | M9: 45780 | N9: sábado | O9: 20 | P9: Dinheiro F | Q9: Bonificação
A10: 45781 | B10: domingo | C10: 25.5 | D10: Pix | E10: Sorvete | M10: 45781 | N10: domingo | O10: - | P10: - | Q10: -
A11: 45782 | B11: segunda-feira | C11: 500 | D11: Pix | E11: Aluguel | M11: 45782 | N11: segunda-feira | O11: - | P11: - | Q11: -
A12: 45783 | B12: terça-feira | C12: 107 | D12: Dinheiro F | E12: Geladeira | M12: 45783 | N12: terça-feira | O12: - | P12: - | Q12: -
A13: 45784 | B13: quarta-feira | C13: 80 | D13: Cartão | E13: Internet | M13: 45784 | N13: quarta-feira | O13: - | P13: - | Q13: -
A14: 45785 | B14: quinta-feira | C14: 384.7 | D14: Pix | E14: Estácio | M14: 45785 | N14: quinta-feira | O14: 150 | P14: Dinheiro F | Q14: Estoque
A15: 45786 | B15: sexta-feira | C15: 7 | D15: Dinheiro F | E15: Refrigerante | M15: 45786 | N15: sexta-feira | O15: - | P15: - | Q15: -
A16: 45786 | B16: sexta-feira | C16: 84.53 | D16: Pix | E16: Presente mãe | M16: 45786 | N16: sexta-feira | O16: - | P16: - | Q16: -
A17: 45787 | B17: sábado | C17: 85.5 | D17: Pix | E17: Passagens, sorvete, lanches | M17: 45787 | N17: sábado | O17: 20 | P17: Dinheiro F | Q17: Bonificação
A18: 45788 | B18: domingo | C18: - | D18: - | E18: - | M18: 45788 | N18: domingo | O18: - | P18: - | Q18: -
A19: 45789 | B19: segunda-feira | C19: 132.74 | D19: Pix | E19: Carteira Definitiva | M19: 45789 | N19: segunda-feira | O19: - | P19: - | Q19: -
A20: 45790 | B20: terça-feira | C20: 46.5 | D20: Dinheiro F | E20: Sorvete | M20: 45790 | N20: terça-feira | O20: - | P20: - | Q20: -
A21: 45791 | B21: quarta-feira | C21: - | D21: - | E21: - | M21: 45791 | N21: quarta-feira | O21: - | P21: - | Q21: -
A22: 45792 | B22: quinta-feira | C22: 30 | D22: Pix | E22: Almoço | M22: 45792 | N22: quinta-feira | O22: - | P22: - | Q22: -
A23: 45793 | B23: sexta-feira | C23: 21 | D23: Dinheiro F | E23: Escova de Dente | M23: 45793 | N23: sexta-feira | O23: 679 | P23: Cartão | Q23: Adiantamento
A24: 45794 | B24: sábado | C24: - | D24: - | E24: - | M24: 45794 | N24: sábado | O24: 20 | P24: Dinheiro F | Q24: Bonificação
A25: 45795 | B25: domingo | C25: - | D25: - | E25: - | M25: 45795 | N25: domingo | O25: - | P25: - | Q25: -
A26: 45796 | B26: segunda-feira | C26: - | D26: - | E26: - | M26: 45796 | N26: segunda-feira | O26: - | P26: - | Q26: -
A27: 45797 | B27: terça-feira | C27: 5 | D27: Dinheiro F | E27: Presente Edmar | M27: 45797 | N27: terça-feira | O27: - | P27: - | Q27: -
A28: 45798 | B28: quarta-feira | C28: 34.15 | D28: Dinheiro F | E28: Remédios | M28: 45798 | N28: quarta-feira | O28: - | P28: - | Q28: -
A29: 45799 | B29: quinta-feira | C29: 57.5 | D29: Cartão | E29: Supermercado | M29: 45799 | N29: quinta-feira | O29: - | P29: - | Q29: -
A30: 45800 | B30: sexta-feira | C30: - | D30: - | E30: - | M30: 45800 | N30: sexta-feira | O30: - | P30: - | Q30: -
A31: 45801 | B31: sábado | C31: 8.5 | D31: Dinheiro F | E31: Lanches | M31: 45801 | N31: sábado | O31: - | P31: - | Q31: -
A32: 45802 | B32: domingo | C32: 25 | D32: Dinheiro F | E32: Sorvete | M32: 45802 | N32: domingo | O32: - | P32: - | Q32: -
A33: 45803 | B33: segunda-feira | C33: - | D33: - | E33: - | M33: 45803 | N33: segunda-feira | O33: - | P33: - | Q33: -
A34: 45804 | B34: terça-feira | C34: 6 | D34: Dinheiro F | E34: Refrigerante | M34: 45804 | N34: terça-feira | O34: - | P34: - | Q34: -
A35: 45805 | B35: quarta-feira | C35: 14.5 | D35: Dinheiro F | E35: Lanches | M35: 45805 | N35: quarta-feira | O35: - | P35: - | Q35: -
A36: 45806 | B36: quinta-feira | C36: - | D36: - | E36: - | M36: 45806 | N36: quinta-feira | O36: 1420 | P36: Cartão | Q36: Salário
A37: 45807 | B37: sexta-feira | C37: - | D37: - | E37: - | M37: 45807 | N37: sexta-feira | O37: - | P37: - | Q37: -
A38: 45808 | B38: sábado | C38: - | D38: - | E38: - | M38: 45808 | N38: sábado | O38: 20 | P38: Dinheiro F | Q38: Bonificação

Sheet Junho 2025
A6: Mês | B6: Semana | C6: Saida | D6: Meio | E6: Informação | M6: Mês | N6: Semana | O6: Entrada | P6: Meio | Q6: Informação
A7: 45809 | B7: domingo | C7: - | D7: - | E7: - | G7: =K9-K8 -> -2273.91 | H7: Pix | I7: Dinheiro F | J7: Cartão | K7: Total | M7: 45809 | N7: domingo | O7: - | P7: - | Q7: -
A8: 45810 | B8: segunda-feira | C8: 24 | D8: Pix | E8: Lanche Acumulado | G8: Despesas | H8: =SUMIF(D7:D39,"Pix",C7:C39) -> 4261.98 | I8: =SUMIF(D7:D39,"Dinheiro F",C7:C39) -> 151 | J8: =SUMIF(D7:D39,"Cartão",C7:C39) -> 227.93 | K8: =SUM(H8:J8) -> 4640.91 | M8: 45810 | N8: segunda-feira | O8: 150 | P8: Dinheiro F | Q8: Estoque
A9: 45811 | B9: terça-feira | C9: 20 | D9: Pix | E9: Mãe | G9: Receita | H9: =SUMIF(P7:P39,"Pix",O7:O39) -> 0 | I9: =SUMIF(P7:P39,"Dinheiro F",O7:O39) -> 330 | J9: =SUMIF(P7:P39,"Cartão",O7:O39) -> 2037 | K9: =SUM(H9:J9) -> 2367 | M9: 45811 | N9: terça-feira | O9: - | P9: - | Q9: -
A10: 45812 | B10: quarta-feira | C10: - | D10: - | E10: - | M10: 45812 | N10: quarta-feira | O10: - | P10: - | Q10: -
A11: 45813 | B11: quinta-feira | C11: 500 | D11: Pix | E11: Aluguel | M11: 45813 | N11: quinta-feira | O11: - | P11: - | Q11: -
A12: 45814 | B12: sexta-feira | C12: - | D12: - | E12: - | M12: 45814 | N12: sexta-feira | O12: - | P12: - | Q12: -
A13: 45815 | B13: sábado | C13: 6 | D13: Pix | E13: Lanche | M13: 45815 | N13: sábado | O13: 20 | P13: Dinheiro F | Q13: Bonificação
A14: 45816 | B14: domingo | C14: 24 | D14: Pix | E14: Sorvete | M14: 45816 | N14: domingo | O14: - | P14: - | Q14: -
A15: 45817 | B15: segunda-feira | C15: - | D15: - | E15: - | M15: 45817 | N15: segunda-feira | O15: - | P15: - | Q15: -
A16: 45818 | B16: terça-feira | C16: - | D16: - | E16: - | M16: 45818 | N16: terça-feira | O16: - | P16: - | Q16: -
A17: 45819 | B17: quarta-feira | C17: 19 | D17: Pix | E17: Chocolates | M17: 45819 | N17: quarta-feira | O17: - | P17: - | Q17: -
A18: 45820 | B18: quinta-feira | C18: 18.98 | D18: Pix | E18: Chocolates | M18: 45820 | N18: quinta-feira | O18: - | P18: - | Q18: -
A19: 45821 | B19: sexta-feira | C19: - | D19: - | E19: - | M19: 45821 | N19: sexta-feira | O19: - | P19: - | Q19: -
A20: 45822 | B20: sábado | C20: 79.99 | D20: Cartão | E20: Internet | M20: 45822 | N20: sábado | O20: 20 | P20: Dinheiro F | Q20: Bonificação
A21: 45823 | B21: domingo | C21: 32 | D21: Dinheiro F | E21: Sanduiche | M21: 45823 | N21: domingo | O21: - | P21: - | Q21: -
A22: 45824 | B22: segunda-feira | C22: 20.97 | D22: Cartão | E22: Pasta de Dente | M22: 45824 | N22: segunda-feira | O22: 679 | P22: Cartão | Q22: Adiantamento
A23: 45825 | B23: terça-feira | C23: 2.5 | D23: Dinheiro F | E23: Pão de Queijo | M23: 45825 | N23: terça-feira | O23: - | P23: - | Q23: -
A24: 45826 | B24: quarta-feira | C24: 6 | D24: Pix | E24: Salgado | M24: 45826 | N24: quarta-feira | O24: - | P24: - | Q24: -
A25: 45827 | B25: quinta-feira | C25: 100 | D25: Dinheiro F | E25: Mãe | M25: 45827 | N25: quinta-feira | O25: - | P25: - | Q25: -
A26: 45828 | B26: sexta-feira | C26: - | D26: - | E26: - | M26: 45828 | N26: sexta-feira | O26: - | P26: - | Q26: -
A27: 45829 | B27: sábado | C27: 28 | D27: Cartão | E27: Almoço | M27: 45829 | N27: sábado | O27: 20 | P27: Dinheiro F | Q27: Bonificação
A28: 45830 | B28: domingo | C28: 40 | D28: Cartão | E28: Sorvete | M28: 45830 | N28: domingo | O28: - | P28: - | Q28: -
A29: 45831 | B29: segunda-feira | C29: 36 | D29: Pix | E29: Mãe | M29: 45831 | N29: segunda-feira | O29: - | P29: - | Q29: -
A30: 45832 | B30: terça-feira | C30: 58.97 | D30: Cartão | E30: Desodorante | M30: 45832 | N30: terça-feira | O30: - | P30: - | Q30: -
A31: 45833 | B31: quarta-feira | C31: 3580 | D31: Pix | E31: Computador (Metade) | M31: 45833 | N31: quarta-feira | O31: - | P31: - | Q31: -
A32: 45834 | B32: quinta-feira | C32: 2.5 | D32: Dinheiro F | E32: Pão de Queijo | M32: 45834 | N32: quinta-feira | O32: 1358 | P32: Cartão | Q32: Salário
A33: 45835 | B33: sexta-feira | C33: - | D33: - | E33: - | M33: 45835 | N33: sexta-feira | O33: - | P33: - | Q33: -
A34: 45836 | B34: sábado | C34: 14 | D34: Dinheiro F | E34: Refrigerante | M34: 45836 | N34: sábado | O34: 20 | P34: Dinheiro F | Q34: Bonificação
A35: 45837 | B35: domingo | C35: - | D35: - | E35: - | M35: 45837 | N35: domingo | O35: - | P35: - | Q35: -
A36: 45838 | B36: segunda-feira | C36: 28 | D36: Pix | E36: Almoço | M36: 45838 | N36: segunda-feira | O36: 100 | P36: Dinheiro F | Q36: Free lancer

Sheet Julho 2025
A6: Mês | B6: Semana | C6: Saida | D6: Meio | E6: Informação | M6: Mês | N6: Semana | O6: Entrada | P6: Meio | Q6: Informação
A7: 45839 | B7: terça-feira | C7: - | D7: - | E7: - | G7: =K9-K8 -> 8332.94 | H7: Pix | I7: Dinheiro F | J7: Cartão | K7: Total | M7: 45839 | N7: terça-feira | O7: - | P7: - | Q7: -
A8: 45840 | B8: quarta-feira | C8: - | D8: - | E8: - | G8: Despesas | H8: =SUMIF(D7:D39,"Pix",C7:C39) -> 980.15 | I8: =SUMIF(D7:D39,"Dinheiro F",C7:C39) -> 0 | J8: =SUMIF(D7:D39,"Cartão",C7:C39) -> 149.7 | K8: =SUM(H8:J8) -> 1129.85 | M8: 45840 | N8: quarta-feira | O8: 100 | P8: Dinheiro F | Q8: Free lancer
A9: 45841 | B9: quinta-feira | C9: 88 | D9: Pix | E9: Lanches, sorvete | G9: Receita | H9: =SUMIF(P7:P39,"Pix",O7:O39) -> 0 | I9: =SUMIF(P7:P39,"Dinheiro F",O7:O39) -> 100 | J9: =SUMIF(P7:P39,"Cartão",O7:O39) -> 9362.79 | K9: =SUM(H9:J9) -> 9462.79 | M9: 45841 | N9: quinta-feira | O9: - | P9: - | Q9: -
A10: 45842 | B10: sexta-feira | C10: - | D10: - | E10: - | M10: 45842 | N10: sexta-feira | O10: - | P10: - | Q10: -
A11: 45843 | B11: sábado | C11: - | D11: - | E11: - | M11: 45843 | N11: sábado | O11: - | P11: - | Q11: -
A12: 45844 | B12: domingo | C12: 46 | D12: Cartão | E12: Sorvete | M12: 45844 | N12: domingo | O12: - | P12: - | Q12: -
A13: 45845 | B13: segunda-feira | C13: - | D13: - | E13: - | M13: 45845 | N13: segunda-feira | O13: - | P13: - | Q13: -
A14: 45846 | B14: terça-feira | C14: - | D14: - | E14: - | M14: 45846 | N14: terça-feira | O14: - | P14: - | Q14: -
A15: 45847 | B15: quarta-feira | C15: 49.99 | D15: Cartão | E15: Internet & Crunchyroll | M15: 45847 | N15: quarta-feira | O15: - | P15: - | Q15: -
A16: 45848 | B16: quinta-feira | C16: 20.69 | D16: Pix | E16: Teatro dos finais infelizes | M16: 45848 | N16: quinta-feira | O16: - | P16: - | Q16: -
A17: 45849 | B17: sexta-feira | C17: 30 | D17: Pix | E17: Plano de vida | M17: 45849 | N17: sexta-feira | O17: 5291.79 | P17: Cartão | Q17: Acerto
A18: 45850 | B18: sábado | C18: - | D18: - | E18: - | M18: 45850 | N18: sábado | O18: - | P18: - | Q18: -
A19: 45851 | B19: domingo | C19: 14 | D19: Pix | E19: Porta Copos | M19: 45851 | N19: domingo | O19: - | P19: - | Q19: -
A20: 45852 | B20: segunda-feira | C20: 30 | D20: Pix | E20: Corte de cabelo | M20: 45852 | N20: segunda-feira | O20: - | P20: - | Q20: -
A21: 45853 | B21: terça-feira | C21: 85.86 | D21: Pix | E21: Ida a Estacio | M21: 45853 | N21: terça-feira | O21: - | P21: - | Q21: -
A22: 45854 | B22: quarta-feira | C22: 100 | D22: Pix | E22: Mãe | M22: 45854 | N22: quarta-feira | O22: - | P22: - | Q22: -
A23: 45855 | B23: quinta-feira | C23: - | D23: - | E23: - | M23: 45855 | N23: quinta-feira | O23: - | P23: - | Q23: -
A24: 45856 | B24: sexta-feira | C24: - | D24: - | E24: - | M24: 45856 | N24: sexta-feira | O24: - | P24: - | Q24: -
A25: 45857 | B25: sábado | C25: 500 | D25: Pix | E25: Aluguel | M25: 45857 | N25: sábado | O25: - | P25: - | Q25: -
A26: 45858 | B26: domingo | C26: 53.71 | D26: Cartão | E26: Sorvete / Pães | M26: 45858 | N26: domingo | O26: - | P26: - | Q26: -
A27: 45859 | B27: segunda-feira | C27: 11.6 | D27: Pix | E27: Metrô | M27: 45859 | N27: segunda-feira | O27: - | P27: - | Q27: -
A28: 45860 | B28: terça-feira | C28: - | D28: - | E28: - | M28: 45860 | N28: terça-feira | O28: 4071 | P28: Cartão | Q28: Multa recisória
A29: 45861 | B29: quarta-feira | C29: - | D29: - | E29: - | M29: 45861 | N29: quarta-feira | O29: - | P29: - | Q29: -
A30: 45862 | B30: quinta-feira | C30: - | D30: - | E30: - | M30: 45862 | N30: quinta-feira | O30: - | P30: - | Q30: -
A31: 45863 | B31: sexta-feira | C31: 50 | D31: Pix | E31: TG | M31: 45863 | N31: sexta-feira | O31: - | P31: - | Q31: -
A32: 45864 | B32: sábado | C32: 50 | D32: Pix | E32: Mãe | M32: 45864 | N32: sábado | O32: - | P32: - | Q32: -
A33: 45865 | B33: domingo | C33: - | D33: - | E33: - | M33: 45865 | N33: domingo | O33: - | P33: - | Q33: -
A34: 45866 | B34: segunda-feira | C34: - | D34: - | E34: - | M34: 45866 | N34: segunda-feira | O34: - | P34: - | Q34: -
A35: 45867 | B35: terça-feira | C35: - | D35: - | E35: - | M35: 45867 | N35: terça-feira | O35: - | P35: - | Q35: -
A36: 45868 | B36: quarta-feira | C36: - | D36: - | E36: - | M36: 45868 | N36: quarta-feira | O36: - | P36: - | Q36: -
A37: 45869 | B37: quinta-feira | C37: - | D37: - | E37: - | M37: 45869 | N37: quinta-feira | O37: - | P37: - | Q37: -

Sheet Agosto 2025
A6: Mês | B6: Semana | C6: Saida | D6: Meio | E6: Informação | M6: Mês | N6: Semana | O6: Entrada | P6: Meio | Q6: Informação
A7: 45870 | B7: Sexta-feira | C7: - | D7: - | E7: - | G7: =K9-K8 -> -525.82 | H7: Pix | I7: Dinheiro F | J7: Cartão | K7: Total | M7: 45870 | N7: Sexta-feira | O7: - | P7: - | Q7: -
A8: 45871 | B8: sábado | C8: 48 | D8: Pix | E8: Minas Shopping a pé | G8: Despesas | H8: =SUMIF(D7:D43,"Pix",C7:C43) -> 2337.82 | I8: =SUMIF(D7:D43,"Dinheiro F",C7:C43) -> 68 | J8: =SUMIF(D7:D43,"Cartão",C7:C43) -> 0 | K8: =SUM(H8:J8) -> 2405.82 | M8: 45871 | N8: sábado | O8: - | P8: - | Q8: -
A9: 45872 | B9: domingo | C9: 120 | D9: Pix | E9: Mãe | G9: Receita | H9: =SUMIF(P7:P43,"Pix",O7:O43) -> 0 | I9: =SUMIF(P7:P43,"Dinheiro F",O7:O43) -> 1880 | J9: =SUMIF(P7:P43,"Cartão",O7:O43) -> 0 | K9: =SUM(H9:J9) -> 1880 | M9: 45872 | N9: domingo | O9: - | P9: - | Q9: -
A10: 45873 | B10: segunda-feira | C10: - | D10: - | E10: - | M10: 45873 | N10: segunda-feira | O10: - | P10: - | Q10: -
A11: 45874 | B11: terça-feira | C11: 27 | D11: Pix | E11: Sorvete | M11: 45874 | N11: terça-feira | O11: - | P11: - | Q11: -
A12: 45875 | B12: quarta-feira | C12: - | D12: - | E12: - | M12: 45875 | N12: quarta-feira | O12: - | P12: - | Q12: -
A13: 45876 | B13: quinta-feira | C13: - | D13: - | E13: - | M13: 45876 | N13: quinta-feira | O13: - | P13: - | Q13: -
A14: 45877 | B14: sexta-feira | C14: - | D14: - | E14: - | M14: 45877 | N14: sexta-feira | O14: - | P14: - | Q14: -
A15: 45878 | B15: sábado | C15: - | D15: - | E15: - | M15: 45878 | N15: sábado | O15: - | P15: - | Q15: -
A16: 45879 | B16: domingo | C16: - | D16: - | E16: - | M16: 45879 | N16: domingo | O16: - | P16: - | Q16: -
A17: 45880 | B17: segunda-feira | C17: - | D17: - | E17: - | M17: 45880 | N17: segunda-feira | O17: - | P17: - | Q17: -
A18: 45881 | B18: terça-feira | C18: - | D18: - | E18: - | M18: 45881 | N18: terça-feira | O18: - | P18: - | Q18: -
A19: 45882 | B19: quarta-feira | C19: - | D19: - | E19: - | M19: 45882 | N19: quarta-feira | O19: - | P19: - | Q19: -
A20: 45883 | B20: quinta-feira | C20: 17 | D20: Pix | E20: Milkshake | M20: 45883 | N20: quinta-feira | O20: - | P20: - | Q20: -
A21: 45884 | B21: sexta-feira | C21: - | D21: - | E21: - | M21: 45884 | N21: sexta-feira | O21: - | P21: - | Q21: -
A22: 45885 | B22: sábado | C22: - | D22: - | E22: - | M22: 45885 | N22: sábado | O22: - | P22: - | Q22: -
A23: 45886 | B23: domingo | C23: - | D23: - | E23: - | M23: 45886 | N23: domingo | O23: - | P23: - | Q23: -
A24: 45887 | B24: segunda-feira | C24: 30 | D24: Pix | E24: Internet | M24: 45887 | N24: segunda-feira | O24: - | P24: - | Q24: -
A25: 45888 | B25: terça-feira | C25: 100 | D25: Pix | E25: Passagem | M25: 45888 | N25: terça-feira | O25: - | P25: - | Q25: -
A26: 45888 | B26: terça-feira | C26: 80 | D26: Pix | E26: Uber e Lanche Abertura Estácio | M26: 45888 | N26: terça-feira | O26: - | P26: - | Q26: -
A27: 45889 | B27: quarta-feira | C27: 500 | D27: Pix | E27: Aluguel | M27: 45889 | N27: quarta-feira | O27: - | P27: - | Q27: -
A28: 45890 | B28: quinta-feira | C28: 424.06 | D28: Pix | E28: Camera presente Victória | M28: 45890 | N28: quinta-feira | O28: 1880 | P28: Dinheiro F | Q28: Seguro desemprego
A29: 45890 | B29: quinta-feira | C29: 384.74 | D29: Pix | E29: Mensalidade Estácio | M29: 45890 | N29: quinta-feira | O29: - | P29: - | Q29: -
A30: 45890 | B30: quinta-feira | C30: 28 | D30: Dinheiro F | E30: Almoço | M30: 45890 | N30: quinta-feira | O30: - | P30: - | Q30: -
A31: 45891 | B31: sexta-feira | C31: 16.78 | D31: Pix | E31: Lanches | M31: 45891 | N31: sexta-feira | O31: - | P31: - | Q31: -
A32: 45892 | B32: sábado | C32: 44.5 | D32: Pix | E32: Sanduiche | M32: 45892 | N32: sábado | O32: - | P32: - | Q32: -
A33: 45893 | B33: domingo | C33: 200 | D33: Pix | E33: Mãe | M33: 45893 | N33: domingo | O33: - | P33: - | Q33: -
A34: 45893 | B34: domingo | C34: 120 | D34: Pix | E34: Filme presente Victória | M34: 45893 | N34: domingo | O34: - | P34: - | Q34: -
A35: 45894 | B35: segunda-feira | C35: 58 | D35: Pix | E35: Frutas em geral | M35: 45894 | N35: segunda-feira | O35: - | P35: - | Q35: -
A36: 45895 | B36: terça-feira | C36: - | D36: - | E36: - | M36: 45895 | N36: terça-feira | O36: - | P36: - | Q36: -
A37: 45896 | B37: quarta-feira | C37: 50 | D37: Pix | E37: Mãe | M37: 45896 | N37: quarta-feira | O37: - | P37: - | Q37: -
A38: 45897 | B38: quinta-feira | C38: 17.74 | D38: Pix | E38: Leite, Refrigerante | M38: 45897 | N38: quinta-feira | O38: - | P38: - | Q38: -
A39: 45898 | B39: sexta-feira | C39: 100 | D39: Pix | E39: Passagem | M39: 45898 | N39: sexta-feira | O39: - | P39: - | Q39: -
A40: 45899 | B40: sábado | C40: - | D40: - | E40: - | M40: 45899 | N40: sábado | O40: - | P40: - | Q40: -
A41: 45900 | B41: domingo | C41: 40 | D41: Dinheiro F | E41: Lanches | M41: 45900 | N41: domingo | O41: - | P41: - | Q41: -

Sheet Setembro 2025
A6: Mês | B6: Semana | C6: Saida | D6: Meio | E6: Informação | M6: Mês | N6: Semana | O6: Entrada | P6: Meio | Q6: Informação
A7: 45901 | B7: Segunda-feira | C7: - | D7: - | E7: - | G7: =K9-K8 -> 282.88 | H7: Pix | I7: Dinheiro F | J7: Cartão | K7: Total | M7: 45901 | N7: Segunda-feira | O7: - | P7: - | Q7: -
A8: 45902 | B8: terça-feira | C8: - | D8: - | E8: - | G8: Despesas | H8: =SUMIF(D7:D43,"Pix",C7:C43) -> 1472.18 | I8: =SUMIF(D7:D43,"Dinheiro F",C7:C43) -> 0 | J8: =SUMIF(D7:D43,"Cartão",C7:C43) -> 240.54 | K8: =SUM(H8:J8) -> 1712.72 | M8: 45902 | N8: terça-feira | O8: - | P8: - | Q8: -
A9: 45903 | B9: quarta-feira | C9: 3.26 | D9: Cartão | E9: Pão de queijo | G9: Receita | H9: =SUMIF(P7:P43,"Pix",O7:O43) -> 50 | I9: =SUMIF(P7:P43,"Dinheiro F",O7:O43) -> 111.6 | J9: =SUMIF(P7:P43,"Cartão",O7:O43) -> 1834 | K9: =SUM(H9:J9) -> 1995.6 | M9: 45903 | N9: quarta-feira | O9: - | P9: - | Q9: -
A10: 45904 | B10: quinta-feira | C10: 7.99 | D10: Cartão | E10: Pão de queijo | M10: 45904 | N10: quinta-feira | O10: - | P10: - | Q10: -
A11: 45904 | B11: quinta-feira | C11: 59.99 | D11: Pix | E11: Hollow Knight Silksong | M11: 45904 | N11: quinta-feira | O11: - | P11: - | Q11: -
A12: 45904 | B12: quinta-feira | C12: 36.29 | D12: Cartão | E12: Sorvete | M12: 45904 | N12: quinta-feira | O12: - | P12: - | Q12: -
A13: 45905 | B13: sexta-feira | C13: 92.4 | D13: Pix | E13: Ida a Sheila e Desodorante | M13: 45905 | N13: sexta-feira | O13: - | P13: - | Q13: -
A14: 45906 | B14: sábado | C14: - | D14: - | E14: - | M14: 45906 | N14: sábado | O14: - | P14: - | Q14: -
A15: 45907 | B15: domingo | C15: 384.72 | D15: Pix | E15: Estacio | M15: 45907 | N15: domingo | O15: - | P15: - | Q15: -
A16: 45908 | B16: segunda-feira | C16: - | D16: - | E16: - | M16: 45908 | N16: segunda-feira | O16: - | P16: - | Q16: -
A17: 45909 | B17: terça-feira | C17: 24 | D17: Cartão | E17: Crunchyroll | M17: 45909 | N17: terça-feira | O17: - | P17: - | Q17: -
A18: 45910 | B18: quarta-feira | C18: 26.88 | D18: Cartão | E18: Sacolão | M18: 45910 | N18: quarta-feira | O18: - | P18: - | Q18: -
A19: 45911 | B19: quinta-feira | C19: 3 | D19: Cartão | E19: Picolé | M19: 45911 | N19: quinta-feira | O19: - | P19: - | Q19: -
A20: 45912 | B20: sexta-feira | C20: 17.68 | D20: Cartão | E20: Lanches | M20: 45912 | N20: sexta-feira | O20: - | P20: - | Q20: -
A21: 45912 | B21: sexta-feira | C21: 32.08 | D21: Cartão | E21: Ingressos cinema | M21: 45912 | N21: sexta-feira | O21: - | P21: - | Q21: -
A22: 45913 | B22: sábado | C22: - | D22: - | E22: - | M22: 45913 | N22: sábado | O22: - | P22: - | Q22: -
A23: 45914 | B23: domingo | C23: 20 | D23: Pix | E23: Mãe | M23: 45914 | N23: domingo | O23: - | P23: - | Q23: -
A24: 45915 | B24: segunda-feira | C24: 45 | D24: Pix | E24: Almoço | M24: 45915 | N24: segunda-feira | O24: - | P24: - | Q24: -
A25: 45916 | B25: terça-feira | C25: 30 | D25: Pix | E25: Internet | M25: 45916 | N25: terça-feira | O25: - | P25: - | Q25: -
A26: 45916 | B26: terça-feira | C26: 79.26 | D26: Pix | E26: Ida ao cinema | M26: 45916 | N26: terça-feira | O26: - | P26: - | Q26: -
A27: 45917 | B27: quarta-feira | C27: 3.33 | D27: Pix | E27: Pão de queijo | M27: 45917 | N27: quarta-feira | O27: 1834 | P27: Cartão | Q27: Seguro
A28: 45918 | B28: quinta-feira | C28: 56.77 | D28: Pix | E28: Frutas e leite | M28: 45918 | N28: quinta-feira | O28: - | P28: - | Q28: -
A29: 45918 | B29: quinta-feira | C29: 109.99 | D29: Pix | E29: Presente luciano | M29: 45918 | N29: quinta-feira | O29: - | P29: - | Q29: -
A30: 45919 | B30: sexta-feira | C30: 26.46 | D30: Pix | E30: Almoço | M30: 45919 | N30: sexta-feira | O30: - | P30: - | Q30: -
A31: 45920 | B31: sábado | C31: 415 | D31: Pix | E31: Aluguel | M31: 45920 | N31: sábado | O31: 111.6 | P31: Dinheiro F | Q31: Free lancer
A32: 45921 | B32: domingo | C32: - | D32: - | E32: - | M32: 45921 | N32: domingo | O32: - | P32: - | Q32: -
A33: 45922 | B33: segunda-feira | C33: 100 | D33: Pix | E33: Passagem | M33: 45922 | N33: segunda-feira | O33: - | P33: - | Q33: -
A34: 45923 | B34: terça-feira | C34: 7.75 | D34: Pix | E34: Frutas | M34: 45923 | N34: terça-feira | O34: - | P34: - | Q34: -
A35: 45924 | B35: quarta-feira | C35: 36.78 | D35: Cartão | E35: Sorvete | M35: 45924 | N35: quarta-feira | O35: - | P35: - | Q35: -
A36: 45925 | B36: quinta-feira | C36: 25.34 | D36: Pix | E36: Frutas e leite | M36: 45925 | N36: quinta-feira | O36: - | P36: - | Q36: -
A37: 45926 | B37: sexta-feira | C37: 16.17 | D37: Pix | E37: Lanches | M37: 45926 | N37: sexta-feira | O37: - | P37: - | Q37: -
A38: 45927 | B38: sábado | C38: - | D38: - | E38: - | M38: 45927 | N38: sábado | O38: - | P38: - | Q38: -
A39: 45928 | B39: domingo | C39: 22 | D39: Cartão | E39: Frutas | M39: 45928 | N39: domingo | O39: - | P39: - | Q39: -
A40: 45929 | B40: segunda-feira | C40: - | D40: - | E40: - | M40: 45929 | N40: segunda-feira | O40: - | P40: - | Q40: -
A41: 45930 | B41: terça-feira | C41: 30.58 | D41: Cartão | E41: Almoço | M41: 45930 | N41: terça-feira | O41: 50 | P41: Pix | Q41: Ajuda Lucas

Sheet Outubro 2025
A6: Mês | B6: Semana | C6: Saida | D6: Meio | E6: Informação | M6: Mês | N6: Semana | O6: Entrada | P6: Meio | Q6: Informação
A7: 45931 | B7: quarta-feira | C7: 4.95 | D7: Cartão | E7: Pão de queijo | G7: =K9-K8 -> -723.86 | H7: Pix | I7: Dinheiro F | J7: Cartão | K7: Total | M7: 45931 | N7: quarta-feira | O7: - | P7: - | Q7: -
A8: 45932 | B8: quinta-feira | C8: 42.17 | D8: Cartão | E8: Frutas | G8: Despesas | H8: =SUMIF(D7:D43,"Pix",C7:C43) -> 2271.3 | I8: =SUMIF(D7:D43,"Dinheiro F",C7:C43) -> 12 | J8: =SUMIF(D7:D43,"Cartão",C7:C43) -> 418.56 | K8: =SUM(H8:J8) -> 2701.86 | M8: 45932 | N8: quinta-feira | O8: - | P8: - | Q8: -
A9: 45933 | B9: sexta-feira | C9: - | D9: - | E9: - | G9: Receita | H9: =SUMIF(P7:P43,"Pix",O7:O43) -> 144 | I9: =SUMIF(P7:P43,"Dinheiro F",O7:O43) -> 0 | J9: =SUMIF(P7:P43,"Cartão",O7:O43) -> 1834 | K9: =SUM(H9:J9) -> 1978 | M9: 45933 | N9: sexta-feira | O9: - | P9: - | Q9: -
A10: 45934 | B10: sábado | C10: - | D10: - | E10: - | M10: 45934 | N10: sábado | O10: - | P10: - | Q10: -
A11: 45935 | B11: domingo | C11: - | D11: - | E11: - | M11: 45935 | N11: domingo | O11: - | P11: - | Q11: -
A12: 45936 | B12: segunda-feira | C12: 9.96 | D12: Cartão | E12: Refrigerante | M12: 45936 | N12: segunda-feira | O12: - | P12: - | Q12: -
A13: 45937 | B13: terça-feira | C13: 384.72 | D13: Pix | E13: Estacio | M13: 45937 | N13: terça-feira | O13: - | P13: - | Q13: -
A14: 45938 | B14: quarta-feira | C14: - | D14: - | E14: - | M14: 45938 | N14: quarta-feira | O14: - | P14: - | Q14: -
A15: 45939 | B15: quinta-feira | C15: - | D15: - | E15: - | M15: 45939 | N15: quinta-feira | O15: - | P15: - | Q15: -
A16: 45940 | B16: sexta-feira | C16: 100 | D16: Pix | E16: Mãe | M16: 45940 | N16: sexta-feira | O16: - | P16: - | Q16: -
A17: 45941 | B17: sábado | C17: - | D17: - | E17: - | M17: 45941 | N17: sábado | O17: - | P17: - | Q17: -
A18: 45942 | B18: domingo | C18: - | D18: - | E18: - | M18: 45942 | N18: domingo | O18: - | P18: - | Q18: -
A19: 45943 | B19: segunda-feira | C19: 30 | D19: Pix | E19: Internet | M19: 45943 | N19: segunda-feira | O19: - | P19: - | Q19: -
A20: 45944 | B20: terça-feira | C20: 29.02 | D20: Cartão | E20: Frutas | M20: 45944 | N20: terça-feira | O20: - | P20: - | Q20: -
A21: 45945 | B21: quarta-feira | C21: 4.95 | D21: Cartão | E21: Pão de queijo | M21: 45945 | N21: quarta-feira | O21: - | P21: - | Q21: -
A22: 45946 | B22: quinta-feira | C22: 10.66 | D22: Cartão | E22: Leite | M22: 45946 | N22: quinta-feira | O22: - | P22: - | Q22: -
A23: 45947 | B23: sexta-feira | C23: 20.23 | D23: Pix | E23: Lanches | M23: 45947 | N23: sexta-feira | O23: 1834 | P23: Cartão | Q23: Seguro
A24: 45948 | B24: sábado | C24: 100 | D24: Pix | E24: Passagem | M24: 45948 | N24: sábado | O24: - | P24: - | Q24: -
A25: 45949 | B25: domingo | C25: 20.7 | D25: Pix | E25: Uber lucas | M25: 45949 | N25: domingo | O25: - | P25: - | Q25: -
A26: 45950 | B26: segunda-feira | C26: 172.39 | D26: Cartão | E26: Ida ao Boliche | M26: 45950 | N26: segunda-feira | O26: - | P26: - | Q26: -
A27: 45950 | B27: segunda-feira | C27: 467 | D27: Pix | E27: Aluguel | M27: 45950 | N27: segunda-feira | O27: - | P27: - | Q27: -
A28: 45951 | B28: terça-feira | C28: 20 | D28: Pix | E28: Mãe | M28: 45951 | N28: terça-feira | O28: - | P28: - | Q28: -
A29: 45951 | B29: terça-feira | C29: 15.65 | D29: Pix | E29: Frutas | M29: 45951 | N29: terça-feira | O29: - | P29: - | Q29: -
A30: 45952 | B30: quarta-feira | C30: 3.39 | D30: Cartão | E30: Pão de queijo | M30: 45952 | N30: quarta-feira | O30: - | P30: - | Q30: -
A31: 45953 | B31: quinta-feira | C31: - | D31: - | E31: - | M31: 45953 | N31: quinta-feira | O31: 84 | P31: Pix | Q31: Ajuda Lucas
A32: 45954 | B32: sexta-feira | C32: 31.32 | D32: Cartão | E32: Sacolão | M32: 45954 | N32: sexta-feira | O32: - | P32: - | Q32: -
A33: 45954 | B33: sexta-feira | C33: 73 | D33: Pix | E33: Sanduiche | M33: 45954 | N33: sexta-feira | O33: - | P33: - | Q33: -
A34: 45955 | B34: sábado | C34: 24.38 | D34: Cartão | E34: Padaria | M34: 45955 | N34: sábado | O34: - | P34: - | Q34: -
A35: 45956 | B35: domingo | C35: - | D35: - | E35: - | M35: 45956 | N35: domingo | O35: - | P35: - | Q35: -
A36: 45957 | B36: segunda-feira | C36: 12 | D36: Dinheiro F | E36: Sorvete | M36: 45957 | N36: segunda-feira | O36: 60 | P36: Pix | Q36: Luciano
A37: 45958 | B37: terça-feira | C37: 39.08 | D37: Cartão | E37: Sacolão | M37: 45958 | N37: terça-feira | O37: - | P37: - | Q37: -
A38: 45959 | B38: quarta-feira | C38: 20.33 | D38: Cartão | E38: Padaria | M38: 45959 | N38: quarta-feira | O38: - | P38: - | Q38: -
A39: 45959 | B39: quarta-feira | C39: 1040 | D39: Pix | E39: Auto Escola Moto | M39: 45959 | N39: quarta-feira | O39: - | P39: - | Q39: -
A40: 45960 | B40: quinta-feira | C40: 12.48 | D40: Cartão | E40: Epa | M40: 45960 | N40: quinta-feira | O40: - | P40: - | Q40: -
A41: 45961 | B41: sexta-feira | C41: 13.48 | D41: Cartão | E41: Lanches | M41: 45961 | N41: sexta-feira | O41: - | P41: - | Q41: -

Sheet Novembro 2025
A6: Mês | B6: Semana | C6: Saida | D6: Meio | E6: Informação | M6: Mês | N6: Semana | O6: Entrada | P6: Meio | Q6: Informação
A7: 45962 | B7: sábado | C7: 100 | D7: Pix | E7: Passagem | G7: =K9-K8 -> -1043.94 | H7: Pix | I7: Dinheiro F | J7: Cartão | K7: Total | M7: 45962 | N7: sábado | O7: - | P7: - | Q7: -
A8: 45963 | B8: domingo | C8: 4.28 | D8: Cartão | E8: Leite | G8: Despesas | H8: =SUMIF(D7:D38,"Pix",C7:C38) -> 1366.41 | I8: =SUMIF(D7:D38,"Dinheiro F",C7:C38) -> 0 | J8: =SUMIF(D7:D38,"Cartão",C7:C38) -> 689.13 | K8: =SUM(H8:J8) -> 2055.54 | M8: 45963 | N8: domingo | O8: - | P8: - | Q8: -
A9: 45964 | B9: segunda-feira | C9: - | D9: - | E9: - | G9: Receita | H9: =SUMIF(P7:P38,"Pix",O7:O38) -> 900 | I9: =SUMIF(P7:P38,"Dinheiro F",O7:O38) -> 111.6 | J9: =SUMIF(P7:P38,"Cartão",O7:O38) -> 0 | K9: =SUM(H9:J9) -> 1011.6 | M9: 45964 | N9: segunda-feira | O9: - | P9: - | Q9: -
A10: 45965 | B10: terça-feira | C10: 28 | D10: Cartão | E10: Sorvete | M10: 45965 | N10: terça-feira | O10: - | P10: - | Q10: -
A11: 45966 | B11: quarta-feira | C11: 99.9 | D11: Pix | E11: Presente Mãe powerbank | M11: 45966 | N11: quarta-feira | O11: - | P11: - | Q11: -
A12: 45967 | B12: quinta-feira | C12: 8 | D12: Cartão | E12: Lanche | M12: 45967 | N12: quinta-feira | O12: - | P12: - | Q12: -
A13: 45968 | B13: sexta-feira | C13: 118.17 | D13: Cartão | E13: Internet, Uber e futebol | M13: 45968 | N13: sexta-feira | O13: - | P13: - | Q13: -
A14: 45969 | B14: sábado | C14: 384.72 | D14: Pix | E14: Estacio | M14: 45969 | N14: sábado | O14: - | P14: - | Q14: -
A15: 45970 | B15: domingo | C15: - | D15: - | E15: - | M15: 45970 | N15: domingo | O15: - | P15: - | Q15: -
A16: 45971 | B16: segunda-feira | C16: - | D16: - | E16: - | M16: 45971 | N16: segunda-feira | O16: - | P16: - | Q16: -
A17: 45972 | B17: terça-feira | C17: 240 | D17: Cartão | E17: Auto Escola e lanche | M17: 45972 | N17: terça-feira | O17: - | P17: - | Q17: -
A18: 45973 | B18: quarta-feira | C18: 3.59 | D18: Cartão | E18: Pão de queijo | M18: 45973 | N18: quarta-feira | O18: - | P18: - | Q18: -
A19: 45974 | B19: quinta-feira | C19: 5.5 | D19: Cartão | E19: Café | M19: 45974 | N19: quinta-feira | O19: - | P19: - | Q19: -
A20: 45975 | B20: sexta-feira | C20: 150 | D20: Cartão | E20: Passagem + Presente natale | M20: 45975 | N20: sexta-feira | O20: 900 | P20: Pix | Q20: Seguro (4/5)
A21: 45976 | B21: sábado | C21: 67.59 | D21: Cartão | E21: Uber e Epa | M21: 45976 | N21: sábado | O21: 111.6 | P21: Dinheiro F | Q21: Free lancer
A22: 45977 | B22: domingo | C22: - | D22: - | E22: - | M22: 45977 | N22: domingo | O22: - | P22: - | Q22: -
A23: 45978 | B23: segunda-feira | C23: - | D23: - | E23: - | M23: 45978 | N23: segunda-feira | O23: - | P23: - | Q23: -
A24: 45979 | B24: terça-feira | C24: 140 | D24: Pix | E24: Auto Escola Moto | M24: 45979 | N24: terça-feira | O24: - | P24: - | Q24: -
A25: 45980 | B25: quarta-feira | C25: 500 | D25: Pix | E25: Aluguel | M25: 45980 | N25: quarta-feira | O25: - | P25: - | Q25: -
A26: 45981 | B26: quinta-feira | C26: - | D26: - | E26: - | M26: 45981 | N26: quinta-feira | O26: - | P26: - | Q26: -
A27: 45982 | B27: sexta-feira | C27: - | D27: - | E27: - | M27: 45982 | N27: sexta-feira | O27: - | P27: - | Q27: -
A28: 45983 | B28: sábado | C28: - | D28: - | E28: - | M28: 45983 | N28: sábado | O28: - | P28: - | Q28: -
A29: 45984 | B29: domingo | C29: - | D29: - | E29: - | M29: 45984 | N29: domingo | O29: - | P29: - | Q29: -
A30: 45985 | B30: segunda-feira | C30: 31 | D30: Pix | E30: Sorvete | M30: 45985 | N30: segunda-feira | O30: - | P30: - | Q30: -
A31: 45986 | B31: terça-feira | C31: 32.08 | D31: Pix | E31: Lanches | M31: 45986 | N31: terça-feira | O31: - | P31: - | Q31: -
A32: 45987 | B32: quarta-feira | C32: 5.5 | D32: Pix | E32: Café | M32: 45987 | N32: quarta-feira | O32: - | P32: - | Q32: -
A33: 45988 | B33: quinta-feira | C33: 73.21 | D33: Pix | E33: Headfone | M33: 45988 | N33: quinta-feira | O33: - | P33: - | Q33: -
A34: 45989 | B34: sexta-feira | C34: 64 | D34: Cartão | E34: Lanches | M34: 45989 | N34: sexta-feira | O34: - | P34: - | Q34: -
A35: 45990 | B35: sábado | C35: - | D35: - | E35: - | M35: 45990 | N35: sábado | O35: - | P35: - | Q35: -
A36: 45991 | B36: domingo | C36: - | D36: - | E36: - | M36: 45991 | N36: domingo | O36: - | P36: - | Q36: -

Sheet Dezembro 2025
A6: Mês | B6: Semana | C6: Saida | D6: Meio | E6: Informação | M6: Mês | N6: Semana | O6: Entrada | P6: Meio | Q6: Informação
A7: 45992 | B7: segunda-feira | C7: 35 | D7: Pix | E7: Mãe | G7: =K9-K8 -> -924.93 | H7: Pix | I7: Dinheiro F | J7: Cartão | K7: Total | M7: 45992 | N7: segunda-feira | O7: - | P7: - | Q7: -
A8: 45993 | B8: terça-feira | C8: 12.11 | D8: Cartão | E8: Frutas | G8: Despesas | H8: =SUMIF(D7:D40,"Pix",C7:C40) -> 1764.07 | I8: =SUMIF(D7:D40,"Dinheiro F",C7:C40) -> 0 | J8: =SUMIF(D7:D40,"Cartão",C7:C40) -> 60.86 | K8: =SUM(H8:J8) -> 1824.93 | M8: 45993 | N8: terça-feira | O8: - | P8: - | Q8: -
A9: 45994 | B9: quarta-feira | C9: - | D9: - | E9: - | G9: Receita | H9: =SUMIF(P7:P40,"Pix",O7:O40) -> 900 | I9: =SUMIF(P7:P40,"Dinheiro F",O7:O40) -> 0 | J9: =SUMIF(P7:P40,"Cartão",O7:O40) -> 0 | K9: =SUM(H9:J9) -> 900 | M9: 45994 | N9: quarta-feira | O9: - | P9: - | Q9: -
A10: 45995 | B10: quinta-feira | C10: - | D10: - | E10: - | M10: 45995 | N10: quinta-feira | O10: - | P10: - | Q10: -
A11: 45996 | B11: sexta-feira | C11: - | D11: - | E11: - | M11: 45996 | N11: sexta-feira | O11: - | P11: - | Q11: -
A12: 45997 | B12: sábado | C12: - | D12: - | E12: - | M12: 45997 | N12: sábado | O12: - | P12: - | Q12: -
A13: 45998 | B13: domingo | C13: - | D13: - | E13: - | M13: 45998 | N13: domingo | O13: - | P13: - | Q13: -
A14: 45999 | B14: segunda-feira | C14: 197.9 | D14: Pix | E14: Capacete e Internet | M14: 45999 | N14: segunda-feira | O14: - | P14: - | Q14: -
A15: 46000 | B15: terça-feira | C15: 384.72 | D15: Pix | E15: Estacio | M15: 46000 | N15: terça-feira | O15: - | P15: - | Q15: -
A16: 46001 | B16: quarta-feira | C16: - | D16: - | E16: - | M16: 46001 | N16: quarta-feira | O16: - | P16: - | Q16: -
A17: 46002 | B17: quinta-feira | C17: - | D17: - | E17: - | M17: 46002 | N17: quinta-feira | O17: 900 | P17: Pix | Q17: Seguro
A18: 46003 | B18: sexta-feira | C18: - | D18: - | E18: - | M18: 46003 | N18: sexta-feira | O18: - | P18: - | Q18: -
A19: 46004 | B19: sábado | C19: - | D19: - | E19: - | M19: 46004 | N19: sábado | O19: - | P19: - | Q19: -
A20: 46005 | B20: domingo | C20: - | D20: - | E20: - | M20: 46005 | N20: domingo | O20: - | P20: - | Q20: -
A21: 46006 | B21: segunda-feira | C21: - | D21: - | E21: - | M21: 46006 | N21: segunda-feira | O21: - | P21: - | Q21: -
A22: 46007 | B22: terça-feira | C22: - | D22: - | E22: - | M22: 46007 | N22: terça-feira | O22: - | P22: - | Q22: -
A23: 46008 | B23: quarta-feira | C23: 440 | D23: Pix | E23: Auto Escola moto | M23: 46008 | N23: quarta-feira | O23: - | P23: - | Q23: -
A24: 46009 | B24: quinta-feira | C24: - | D24: - | E24: - | M24: 46009 | N24: quinta-feira | O24: - | P24: - | Q24: -
A25: 46010 | B25: sexta-feira | C25: 500 | D25: Pix | E25: Aluguel | M25: 46010 | N25: sexta-feira | O25: - | P25: - | Q25: -
A26: 46011 | B26: sábado | C26: - | D26: - | E26: - | M26: 46011 | N26: sábado | O26: - | P26: - | Q26: -
A27: 46012 | B27: domingo | C27: - | D27: - | E27: - | M27: 46012 | N27: domingo | O27: - | P27: - | Q27: -
A28: 46013 | B28: segunda-feira | C28: - | D28: - | E28: - | M28: 46013 | N28: segunda-feira | O28: - | P28: - | Q28: -
A29: 46014 | B29: terça-feira | C29: - | D29: - | E29: - | M29: 46014 | N29: terça-feira | O29: - | P29: - | Q29: -
A30: 46015 | B30: quarta-feira | C30: - | D30: - | E30: - | M30: 46015 | N30: quarta-feira | O30: - | P30: - | Q30: -
A31: 46016 | B31: quinta-feira | C31: - | D31: - | E31: - | M31: 46016 | N31: quinta-feira | O31: - | P31: - | Q31: -
A32: 46017 | B32: sexta-feira | C32: - | D32: - | E32: - | M32: 46017 | N32: sexta-feira | O32: - | P32: - | Q32: -
A33: 46018 | B33: sábado | C33: 46.46 | D33: Pix | E33: Lanches | M33: 46018 | N33: sábado | O33: - | P33: - | Q33: -
A34: 46019 | B34: domingo | C34: 100 | D34: Pix | E34: Mãe | M34: 46019 | N34: domingo | O34: - | P34: - | Q34: -
A35: 46020 | B35: segunda-feira | C35: - | D35: - | E35: - | M35: 46020 | N35: segunda-feira | O35: - | P35: - | Q35: -
A36: 46021 | B36: terça-feira | C36: 59.99 | D36: Pix | E36: Constance | M36: 46021 | N36: terça-feira | O36: - | P36: - | Q36: -
A37: 46021 | B37: terça-feira | C37: 48.75 | D37: Cartão | E37: Sorvete | M37: 46021 | N37: terça-feira | O37: - | P37: - | Q37: -
A38: 46022 | B38: quarta-feira | C38: - | D38: - | E38: - | M38: 46022 | N38: quarta-feira | O38: - | P38: - | Q38: -

Sheet Janeiro 2025
A6: Mês | B6: Semana | C6: Saida | D6: Meio | E6: Informação | M6: Mês | N6: Semana | O6: Entrada | P6: Meio | Q6: Informação
A7: 45658 | B7: quarta-feira | C7: - | D7: - | E7: - | G7: =K9-K8 -> 597.63 | H7: Pix | I7: Dinheiro F | J7: Cartão | K7: Total | M7: 45658 | N7: quarta-feira | O7: - | P7: - | Q7: -
A8: 45659 | B8: quinta-feira | C8: 32 | D8: Dinheiro F | E8: Sorvete | G8: Despesas | H8: =SUMIF(D7:D41,"Pix",C7:C41) -> 1051.37 | I8: =SUMIF(D7:D41,"Dinheiro F",C7:C41) -> 325.9 | J8: =SUMIF(D7:D41,"Cartão",C7:C41) -> 113.1 | K8: =SUM(H8:J8) -> 1490.37 | M8: 45659 | N8: quinta-feira | O8: - | P8: - | Q8: -
A9: 45660 | B9: sexta-feira | C9: 30 | D9: Dinheiro F | E9: Corte de Cabelo | G9: Receita | H9: =SUMIF(P7:P41,"Pix",O7:O41) -> 1823 | I9: =SUMIF(P7:P41,"Dinheiro F",O7:O41) -> 190 | J9: =SUMIF(P7:P41,"Cartão",O7:O41) -> 75 | K9: =SUM(H9:J9) -> 2088 | M9: 45660 | N9: sexta-feira | O9: - | P9: - | Q9: -
A10: 45661 | B10: sábado | C10: 39 | D10: Dinheiro F | E10: Sanduiche | M10: 45661 | N10: sábado | O10: 170 | P10: Dinheiro F | Q10: Estoque (150), Bonificação
A11: 45662 | B11: domingo | C11: 500 | D11: Pix | E11: Aluguel | M11: 45662 | N11: domingo | O11: - | P11: - | Q11: -
A12: 45663 | B12: segunda-feira | C12: - | D12: - | E12: - | M12: 45663 | N12: segunda-feira | O12: - | P12: - | Q12: -
A13: 45664 | B13: terça-feira | C13: 30.5 | D13: Pix | E13: Internet | M13: 45664 | N13: terça-feira | O13: - | P13: - | Q13: -
A14: 45665 | B14: quarta-feira | C14: 90 | D14: Pix | E14: Mãe (50), Crunchyroll 2 meses | M14: 45665 | N14: quarta-feira | O14: - | P14: - | Q14: -
A15: 45666 | B15: quinta-feira | C15: 22.9 | D15: Dinheiro F | E15: Café | M15: 45666 | N15: quinta-feira | O15: 1171 | P15: Pix | Q15: Salário
A16: 45667 | B16: sexta-feira | C16: 18.9 | D16: Pix | E16: Anuidade Caixa | M16: 45667 | N16: sexta-feira | O16: - | P16: - | Q16: -
A17: 45667 | B17: Sexta-feira | C17: 76 | D17: Dinheiro F | E17: Calça Mãe (56), Lanche | M17: 45667 | N17: sexta-feira | O17: - | P17: - | Q17: -
A18: 45668 | B18: sábado | C18: 42 | D18: Cartão | E18: Uber ida e volta | M18: 45668 | N18: sábado | O18: 20 | P18: Dinheiro F | Q18: Bonificação
A19: 45668 | B19: sábado | C19: 15 | D19: Dinheiro F | E19: Sorvete | M19: 45668 | N19: sábado | O19: - | P19: - | Q19: -
A20: 45669 | B20: domingo | C20: 20 | D20: Pix | E20: Mãe | M20: 45669 | N20: domingo | O20: - | P20: - | Q20: -
A21: 45670 | B21: segunda-feira | C21: - | D21: - | E21: - | M21: 45670 | N21: segunda-feira | O21: - | P21: - | Q21: -
A22: 45671 | B22: terça-feira | C22: 62 | D22: Dinheiro F | E22: Sorvete | M22: 45671 | N22: terça-feira | O22: - | P22: - | Q22: -
A23: 45672 | B23: quarta-feira | C23: - | D23: - | E23: - | M23: 45672 | N23: quarta-feira | O23: - | P23: - | Q23: -
A24: 45673 | B24: quinta-feira | C24: 51 | D24: Pix | E24: Mãe | M24: 45673 | N24: quinta-feira | O24: 632 | P24: Pix | Q24: Adiantamento
A25: 45674 | B25: sexta-feira | C25: 51.1 | D25: Cartão | E25: Uber | M25: 45674 | N25: sexta-feira | O25: - | P25: - | Q25: -
A26: 45675 | B26: sábado | C26: - | D26: - | E26: - | G26: Sorvete | I26: =sumif(E8:E41,G26,C8:C41) -> 167 | M26: 45675 | N26: sábado | O26: - | P26: - | Q26: -
A27: 45676 | B27: domingo | C27: 22 | D27: Dinheiro F | E27: Sorvete | M27: 45676 | N27: domingo | O27: - | P27: - | Q27: -
A28: 45677 | B28: segunda-feira | C28: 8 | D28: Dinheiro F | E28: Refrigerante | M28: 45677 | N28: segunda-feira | O28: - | P28: - | Q28: -
A29: 45678 | B29: terça-feira | C29: 13 | D29: Dinheiro F | E29: Lanches | M29: 45678 | N29: terça-feira | O29: - | P29: - | Q29: -
A30: 45679 | B30: quarta-feira | C30: 142 | D30: Pix | E30: Geladeira | M30: 45679 | N30: quarta-feira | O30: - | P30: - | Q30: -
A31: 45680 | B31: quinta-feira | C31: - | D31: - | E31: - | M31: 45680 | N31: quinta-feira | O31: - | P31: - | Q31: -
A32: 45681 | B32: sexta-feira | C32: - | D32: - | E32: - | M32: 45681 | N32: sexta-feira | O32: - | P32: - | Q32: -
A33: 45682 | B33: sábado | C33: - | D33: - | E33: - | M33: 45682 | N33: sábado | O33: 20 | P33: Pix | Q33: Bonificação
A34: 45682 | B34: sábado | C34: 20 | D34: Cartão | E34: Crunchyroll | M34: 45682 | N34: sábado | O34: - | P34: - | Q34: -
A35: 45683 | B35: domingo | C35: 36 | D35: Pix | E35: Sorvete | M35: 45683 | N35: domingo | O35: - | P35: - | Q35: -
A36: 45683 | B36: domingo | C36: 12 | D36: Pix | E36: Pão | M36: 45683 | N36: domingo | O36: - | P36: - | Q36: -
A37: 45684 | B37: segunda-feira | C37: 20.97 | D37: Pix | E37: Lojas Rede | M37: 45684 | N37: segunda-feira | O37: - | P37: - | Q37: -
A38: 45685 | B38: terça-feira | C38: 30 | D38: Pix | E38: Almoço | M38: 45685 | N38: terça-feira | O38: - | P38: - | Q38: -
A39: 45686 | B39: quarta-feira | C39: 100 | D39: Pix | E39: Mãe | M39: 45686 | N39: quarta-feira | O39: - | P39: - | Q39: -
A40: 45687 | B40: quinta-feira | C40: 6 | D40: Dinheiro F | E40: Lanches | M40: 45687 | N40: quinta-feira | O40: 75 | P40: Cartão | Q40: Limpeza da marquise
A41: 45688 | B41: sexta-feira | C41: - | D41: - | E41: - | M41: 45688 | N41: sexta-feira | O41: - | P41: - | Q41: -
J116: 0

Sheet Março 2025
A6: Mês | B6: Semana | C6: Saida | D6: Meio | E6: Informação | M6: Mês | N6: Semana | O6: Entrada | P6: Meio | Q6: Informação
A7: 45717 | B7: sábado | C7: 125 | D7: Pix | E7: Clube | G7: =K9-K8 -> 817.96 | H7: Pix | I7: Dinheiro F | J7: Cartão | K7: Total | M7: 45717 | N7: sábado | O7: - | P7: - | Q7: -
A8: 45718 | B8: domingo | C8: 20 | D8: Pix | E8: Mãe | G8: Despesas | H8: =SUMIF(D7:D41,"Pix",C7:C41) -> 952.73 | I8: =SUMIF(D7:D41,"Dinheiro F",C7:C41) -> 186 | J8: =SUMIF(D7:D41,"Cartão",C7:C41) -> 676.31 | K8: =SUM(H8:J8) -> 1815.04 | M8: 45718 | N8: domingo | O8: - | P8: - | Q8: -
A9: 45719 | B9: segunda-feira | C9: 53.73 | D9: Pix | E9: Ifood | G9: Receita | H9: =SUMIF(P7:P41,"Pix",O7:O41) -> 22 | I9: =SUMIF(P7:P41,"Dinheiro F",O7:O41) -> 230 | J9: =SUMIF(P7:P41,"Cartão",O7:O41) -> 2381 | K9: =SUM(H9:J9) -> 2633 | M9: 45719 | N9: segunda-feira | O9: - | P9: - | Q9: -
A10: 45720 | B10: terça-feira | C10: 15 | D10: Pix | E10: Plano funerário | M10: 45720 | N10: terça-feira | O10: - | P10: - | Q10: -
A11: 45721 | B11: quarta-feira | C11: 447 | D11: Pix | E11: Aluguel | M11: 45721 | N11: quarta-feira | O11: 1017 | P11: Cartão | Q11: Salário
A12: 45722 | B12: quinta-feira | C12: - | D12: - | E12: - | M12: 45722 | N12: quinta-feira | O12: - | P12: - | Q12: -
A13: 45723 | B13: sexta-feira | C13: - | D13: - | E13: - | M13: 45723 | N13: sexta-feira | O13: - | P13: - | Q13: -
A14: 45724 | B14: sábado | C14: 399.78 | D14: Cartão | E14: Estácio | M14: 45724 | N14: sábado | O14: 20 | P14: Dinheiro F | Q14: Bonificação
A15: 45725 | B15: domingo | C15: - | D15: - | E15: - | M15: 45725 | N15: domingo | O15: - | P15: - | Q15: -
A16: 45726 | B16: segunda-feira | C16: 26 | D16: Dinheiro F | E16: Lanches | M16: 45726 | N16: segunda-feira | O16: 150 | P16: Dinheiro F | Q16: Estoque
A17: 45727 | B17: terça-feira | C17: - | D17: - | E17: - | M17: 45727 | N17: terça-feira | O17: - | P17: - | Q17: -
A18: 45728 | B18: quarta-feira | C18: - | D18: - | E18: - | M18: 45728 | N18: quarta-feira | O18: - | P18: - | Q18: -
A19: 45729 | B19: quinta-feira | C19: 68 | D19: Pix | E19: Presente Sheila | M19: 45729 | N19: quinta-feira | O19: - | P19: - | Q19: -
A20: 45730 | B20: sexta-feira | C20: 50 | D20: Pix | E20: Mãe (Carne) | M20: 45730 | N20: sexta-feira | O20: 632 | P20: Cartão | Q20: Adiantamento
A21: 45731 | B21: sábado | C21: 71 | D21: Dinheiro F | E21: Sorvete | M21: 45731 | N21: sábado | O21: 20 | P21: Dinheiro F | Q21: Bonificação
A22: 45731 | B22: Sábado | C22: 28 | D22: Dinheiro F | E22: Almoço | M22: 45731 | N22: Sábado | O22: - | P22: - | Q22: -
A23: 45732 | B23: domingo | C23: - | D23: - | E23: - | M23: 45732 | N23: domingo | O23: 22 | P23: Pix | Q23: Sorvete
A24: 45733 | B24: segunda-feira | C24: - | D24: - | E24: - | M24: 45733 | N24: segunda-feira | O24: - | P24: - | Q24: -
A25: 45734 | B25: terça-feira | C25: 17 | D25: Pix | E25: Uber Fernanda | M25: 45734 | N25: terça-feira | O25: - | P25: - | Q25: -
A26: 45735 | B26: quarta-feira | C26: 107 | D26: Pix | E26: Geladeira | M26: 45735 | N26: quarta-feira | O26: - | P26: - | Q26: -
A27: 45736 | B27: quinta-feira | C27: 30 | D27: Cartão | E27: Internet | M27: 45736 | N27: quinta-feira | O27: - | P27: - | Q27: -
A28: 45737 | B28: sexta-feira | C28: 61 | D28: Dinheiro F | E28: Sorvete | M28: 45737 | N28: sexta-feira | O28: - | P28: - | Q28: -
A29: 45738 | B29: sábado | C29: - | D29: - | E29: - | M29: 45738 | N29: sábado | O29: 20 | P29: Dinheiro F | Q29: Bonificação
A30: 45739 | B30: domingo | C30: - | D30: - | E30: - | M30: 45739 | N30: domingo | O30: - | P30: - | Q30: -
A31: 45740 | B31: segunda-feira | C31: 20 | D31: Pix | E31: Mãe (Carne) | M31: 45740 | N31: segunda-feira | O31: - | P31: - | Q31: -
A32: 45741 | B32: terça-feira | C32: 50.7 | D32: Cartão | E32: Desodorante | M32: 45741 | N32: terça-feira | O32: - | P32: - | Q32: -
A33: 45741 | B33: terça-feira | C33: 34.9 | D33: Cartão | E33: Café | M33: 45741 | N33: terça-feira | O33: - | P33: - | Q33: -
A34: 45742 | B34: quarta-feira | C34: 28 | D34: Cartão | E34: Salgado | M34: 45742 | N34: quarta-feira | O34: - | P34: - | Q34: -
A35: 45743 | B35: quinta-feira | C35: 13 | D35: Cartão | E35: Enrolado | M35: 45743 | N35: quinta-feira | O35: - | P35: - | Q35: -
A36: 45744 | B36: sexta-feira | C36: 1.93 | D36: Cartão | E36: Suco | M36: 45744 | N36: sexta-feira | O36: 732 | P36: Cartão | Q36: Salário
A37: 45745 | B37: sábado | C37: - | D37: - | E37: - | M37: 45745 | N37: sábado | O37: 20 | P37: Dinheiro F | Q37: Bonificação
A38: 45746 | B38: domingo | C38: 48 | D38: Cartão | E38: Sorvete | M38: 45746 | N38: domingo | O38: - | P38: - | Q38: -
A39: 45747 | B39: segunda-feira | C39: 70 | D39: Cartão | E39: Tenis | M39: 45747 | N39: segunda-feira | O39: - | P39: - | Q39: -
A40: 45747 | B40: segunda-feira | C40: 30 | D40: Pix | E40: Mãe

Sheet Fevereiro 2025
A6: Mês | B6: Semana | C6: Saida | D6: Meio | E6: Informação | M6: Mês | N6: Semana | O6: Entrada | P6: Meio | Q6: Informação
A7: 45689 | B7: sábado | C7: 4 | D7: Dinheiro F | E7: Lanche | G7: =K9-K8 -> 4408.11 | H7: Pix | I7: Dinheiro F | J7: Cartão | K7: Total | M7: 45689 | N7: sábado | O7: - | P7: - | Q7: -
A8: 45690 | B8: domingo | C8: 32 | D8: Pix | E8: Sorvete | G8: Despesas | H8: =SUMIF(D7:D41,"Pix",C7:C41) -> 932 | I8: =SUMIF(D7:D41,"Dinheiro F",C7:C41) -> 300.1 | J8: =SUMIF(D7:D41,"Cartão",C7:C41) -> 581.79 | K8: =SUM(H8:J8) -> 1813.89 | M8: 45690 | N8: domingo | O8: - | P8: - | Q8: -
A9: 45691 | B9: segunda-feira | C9: 10 | D9: Dinheiro F | E9: Bombom | G9: Receita | H9: =SUMIF(P7:P41,"Pix",O7:O41) -> 4000 | I9: =SUMIF(P7:P41,"Dinheiro F",O7:O41) -> 330 | J9: =SUMIF(P7:P41,"Cartão",O7:O41) -> 1892 | K9: =SUM(H9:J9) -> 6222 | M9: 45691 | N9: segunda-feira | O9: - | P9: - | Q9: -
A10: 45691 | B10: segunda-feira | C10: 60 | D10: Cartão | E10: Tênis | M10: 45691 | N10: segunda-feira | O10: - | P10: - | Q10: -
A11: 45691 | B11: segunda-feira | C11: 25 | D11: Pix | E11: Cinto | M11: 45691 | N11: segunda-feira | O11: - | P11: - | Q11: -
A12: 45692 | B12: terça-feira | C12: - | D12: - | E12: - | M12: 45692 | N12: terça-feira | O12: - | P12: - | Q12: -
A13: 45693 | B13: quarta-feira | C13: 500 | D13: Pix | E13: Aluguel | M13: 45693 | N13: quarta-feira | O13: 1260 | P13: Cartão | Q13: Salário
A14: 45694 | B14: quinta-feira | C14: 18.9 | D14: Cartão | E14: Anuidade Caixa | M14: 45694 | N14: quinta-feira | O14: 150 | P14: Dinheiro F | Q14: Estoque
A15: 45695 | B15: sexta-feira | C15: 110 | D15: Dinheiro F | E15: Guarda Roupa | M15: 45695 | N15: sexta-feira | O15: 120 | P15: Dinheiro F | Q15: Horas extras
A16: 45696 | B16: sábado | C16: 15 | D16: Pix | E16: Plano funerário | M16: 45696 | N16: sábado | O16: 20 | P16: Dinheiro F | Q16: Bonificação
A17: 45697 | B17: domingo | C17: 33.4 | D17: Dinheiro F | E17: Pão | M17: 45697 | N17: domingo | O17: - | P17: - | Q17: -
A18: 45698 | B18: segunda-feira | C18: 64 | D18: Dinheiro F | E18: Sorvete | M18: 45698 | N18: segunda-feira | O18: - | P18: - | Q18: -
A19: 45699 | B19: terça-feira | C19: 150 | D19: Pix | E19: Carreto (Mãe) | M19: 45699 | N19: terça-feira | O19: - | P19: - | Q19: -
A20: 45700 | B20: quarta-feira | C20: 18.5 | D20: Dinheiro F | E20: Lanche | M20: 45700 | N20: quarta-feira | O20: - | P20: - | Q20: -
A21: 45701 | B21: quinta-feira | C21: 26 | D21: Cartão | E21: Meias | M21: 45701 | N21: quinta-feira | O21: 4000 | P21: Pix | Q21: TG
A22: 45702 | B22: sexta-feira | C22: - | D22: - | E22: - | M22: 45702 | N22: sexta-feira | O22: 632 | P22: Cartão | Q22: Adiantamento
A23: 45703 | B23: sábado | C23: - | D23: - | E23: - | M23: 45703 | N23: sábado | O23: 20 | P23: Dinheiro F | Q23: Bonificação
A24: 45704 | B24: domingo | C24: 7.11 | D24: Cartão | E24: Sorvete | M24: 45704 | N24: domingo | O24: - | P24: - | Q24: -
A25: 45705 | B25: segunda-feira | C25: 30 | D25: Cartão | E25: Internet | M25: 45705 | N25: segunda-feira | O25: - | P25: - | Q25: -
A26: 45706 | B26: terça-feira | C26: 32 | D26: Cartão | E26: Uber | M26: 45706 | N26: terça-feira | O26: - | P26: - | Q26: -
A27: 45707 | B27: quarta-feira | C27: 47.2 | D27: Dinheiro F | E27: Presente Nívia | M27: 45707 | N27: quarta-feira | O27: - | P27: - | Q27: -
A28: 45708 | B28: quinta-feira | C28: 135 | D28: Pix | E28: Geladeira | M28: 45708 | N28: quinta-feira | O28: - | P28: - | Q28: -
A29: 45709 | B29: sexta-feira | C29: 399.78 | D29: Cartão | E29: Estácio | M29: 45709 | N29: sexta-feira | O29: - | P29: - | Q29: -
A30: 45710 | B30: sábado | C30: - | D30: - | E30: - | M30: 45710 | N30: sábado | O30: 20 | P30: Dinheiro F | Q30: Bonificação
A31: 45711 | B31: domingo | C31: 60 | D31: Pix | E31: Mãe | M31: 45711 | N31: domingo | O31: - | P31: - | Q31: -
A32: 45712 | B32: segunda-feira | C32: 8 | D32: Dinheiro F | E32: Leite | M32: 45712 | N32: segunda-feira | O32: - | P32: - | Q32: -
A33: 45713 | B33: terça-feira | C33: - | D33: - | E33: - | M33: 45713 | N33: terça-feira | O33: - | P33: - | Q33: -
A34: 45714 | B34: quarta-feira | C34: 15 | D34: Pix | E34: Refrigerante | M34: 45714 | N34: quarta-feira | O34: - | P34: - | Q34: -
A35: 45715 | B35: quinta-feira | C35: 5 | D35: Dinheiro F | E35: Sorvete | M35: 45715 | N35: quinta-feira | O35: - | P35: - | Q35: -
A36: 45716 | B36: sexta-feira | C36: 8 | D36: Cartão | E36: Refrigerante | M36: 45716 | N36: sexta-feira | O36: - | P36: - | Q36: -
